PWM/PWM.v
module pwmN #(parameter N = 8)
(
    input wire clk,
    input wire clr,
    input wire [N-1:0] duty,
    input wire [N-1:0] period,
    output reg pwm
);

reg [N-1:0] count;

initial begin
	count = 8'b0000_0000;
end

always @(posedge clk or posedge clr) begin
    if (clr == 1)
        count <= 0;
    else if (count == (period - 1))
        count <= 0;
    else 
        count <= count + 1;
end

always @(*) begin
    if (count < duty)
        pwm <= 1;
    else 
        pwm <= 0;
end

endmodule

PWM/PWM_tb.v
`include "PWM.v"
`timescale 1ns/1ps
module pwm_testbench ();

parameter N = 8;
reg clock;
reg rst;
reg [N-1:0] duty;
reg [N-1:0] period;
wire pwm;

pwmN test_unit(
    .clk(clock),
    .clr(rst),
    .duty(duty),
	.period(period),
	.pwm(pwm)
);

/* clock generation */
initial begin
    clock = 0;
    forever #100 clock = ~clock;
end

integer i = 0;
/* generate data dump */
initial begin
    $dumpfile("PWM.vcd");
    $dumpvars(0, pwm_testbench);

	rst = 1'b0;		/* action */
	period = 255;

	for (i = 0; i < 255; i++)
		#51200 duty = i;
    $finish;
end

initial begin
    $monitor("RST = %d   PWM = %d / %d\n", rst, duty, period);
end

endmodule

PWM/PWM.vcd
$date
	Thu Mar 23 12:44:29 2023
$end
$version
	Icarus Verilog
$end
$timescale
	1ps
$end
$scope module pwm_testbench $end
$var wire 1 ! pwm $end
$var parameter 32 " N $end
$var reg 1 # clock $end
$var reg 8 $ duty [7:0] $end
$var reg 8 % period [7:0] $end
$var reg 1 & rst $end
$var integer 32 ' i [31:0] $end
$scope module test_unit $end
$var wire 1 # clk $end
$var wire 1 & clr $end
$var wire 8 ( duty [7:0] $end
$var wire 8 ) period [7:0] $end
$var parameter 32 * N $end
$var reg 8 + count [7:0] $end
$var reg 1 ! pwm $end
$upscope $end
$upscope $end
$enddefinitions $end
$comment Show the parameter values. $end
$dumpall
b1000 *
b1000 "
$end
#0
$dumpvars
b0 +
b11111111 )
bx (
b0 '
0&
b11111111 %
bx $
0#
0!
$end
#100000
b1 +
1#
#200000
0#
#300000
b10 +
1#
#400000
0#
#500000
b11 +
1#
#600000
0#
#700000
b100 +
1#
#800000
0#
#900000
b101 +
1#
#1000000
0#
#1100000
b110 +
1#
#1200000
0#
#1300000
b111 +
1#
#1400000
0#
#1500000
b1000 +
1#
#1600000
0#
#1700000
b1001 +
1#
#1800000
0#
#1900000
b1010 +
1#
#2000000
0#
#2100000
b1011 +
1#
#2200000
0#
#2300000
b1100 +
1#
#2400000
0#
#2500000
b1101 +
1#
#2600000
0#
#2700000
b1110 +
1#
#2800000
0#
#2900000
b1111 +
1#
#3000000
0#
#3100000
b10000 +
1#
#3200000
0#
#3300000
b10001 +
1#
#3400000
0#
#3500000
b10010 +
1#
#3600000
0#
#3700000
b10011 +
1#
#3800000
0#
#3900000
b10100 +
1#
#4000000
0#
#4100000
b10101 +
1#
#4200000
0#
#4300000
b10110 +
1#
#4400000
0#
#4500000
b10111 +
1#
#4600000
0#
#4700000
b11000 +
1#
#4800000
0#
#4900000
b11001 +
1#
#5000000
0#
#5100000
b11010 +
1#
#5200000
0#
#5300000
b11011 +
1#
#5400000
0#
#5500000
b11100 +
1#
#5600000
0#
#5700000
b11101 +
1#
#5800000
0#
#5900000
b11110 +
1#
#6000000
0#
#6100000
b11111 +
1#
#6200000
0#
#6300000
b100000 +
1#
#6400000
0#
#6500000
b100001 +
1#
#6600000
0#
#6700000
b100010 +
1#
#6800000
0#
#6900000
b100011 +
1#
#7000000
0#
#7100000
b100100 +
1#
#7200000
0#
#7300000
b100101 +
1#
#7400000
0#
#7500000
b100110 +
1#
#7600000
0#
#7700000
b100111 +
1#
#7800000
0#
#7900000
b101000 +
1#
#8000000
0#
#8100000
b101001 +
1#
#8200000
0#
#8300000
b101010 +
1#
#8400000
0#
#8500000
b101011 +
1#
#8600000
0#
#8700000
b101100 +
1#
#8800000
0#
#8900000
b101101 +
1#
#9000000
0#
#9100000
b101110 +
1#
#9200000
0#
#9300000
b101111 +
1#
#9400000
0#
#9500000
b110000 +
1#
#9600000
0#
#9700000
b110001 +
1#
#9800000
0#
#9900000
b110010 +
1#
#10000000
0#
#10100000
b110011 +
1#
#10200000
0#
#10300000
b110100 +
1#
#10400000
0#
#10500000
b110101 +
1#
#10600000
0#
#10700000
b110110 +
1#
#10800000
0#
#10900000
b110111 +
1#
#11000000
0#
#11100000
b111000 +
1#
#11200000
0#
#11300000
b111001 +
1#
#11400000
0#
#11500000
b111010 +
1#
#11600000
0#
#11700000
b111011 +
1#
#11800000
0#
#11900000
b111100 +
1#
#12000000
0#
#12100000
b111101 +
1#
#12200000
0#
#12300000
b111110 +
1#
#12400000
0#
#12500000
b111111 +
1#
#12600000
0#
#12700000
b1000000 +
1#
#12800000
0#
#12900000
b1000001 +
1#
#13000000
0#
#13100000
b1000010 +
1#
#13200000
0#
#13300000
b1000011 +
1#
#13400000
0#
#13500000
b1000100 +
1#
#13600000
0#
#13700000
b1000101 +
1#
#13800000
0#
#13900000
b1000110 +
1#
#14000000
0#
#14100000
b1000111 +
1#
#14200000
0#
#14300000
b1001000 +
1#
#14400000
0#
#14500000
b1001001 +
1#
#14600000
0#
#14700000
b1001010 +
1#
#14800000
0#
#14900000
b1001011 +
1#
#15000000
0#
#15100000
b1001100 +
1#
#15200000
0#
#15300000
b1001101 +
1#
#15400000
0#
#15500000
b1001110 +
1#
#15600000
0#
#15700000
b1001111 +
1#
#15800000
0#
#15900000
b1010000 +
1#
#16000000
0#
#16100000
b1010001 +
1#
#16200000
0#
#16300000
b1010010 +
1#
#16400000
0#
#16500000
b1010011 +
1#
#16600000
0#
#16700000
b1010100 +
1#
#16800000
0#
#16900000
b1010101 +
1#
#17000000
0#
#17100000
b1010110 +
1#
#17200000
0#
#17300000
b1010111 +
1#
#17400000
0#
#17500000
b1011000 +
1#
#17600000
0#
#17700000
b1011001 +
1#
#17800000
0#
#17900000
b1011010 +
1#
#18000000
0#
#18100000
b1011011 +
1#
#18200000
0#
#18300000
b1011100 +
1#
#18400000
0#
#18500000
b1011101 +
1#
#18600000
0#
#18700000
b1011110 +
1#
#18800000
0#
#18900000
b1011111 +
1#
#19000000
0#
#19100000
b1100000 +
1#
#19200000
0#
#19300000
b1100001 +
1#
#19400000
0#
#19500000
b1100010 +
1#
#19600000
0#
#19700000
b1100011 +
1#
#19800000
0#
#19900000
b1100100 +
1#
#20000000
0#
#20100000
b1100101 +
1#
#20200000
0#
#20300000
b1100110 +
1#
#20400000
0#
#20500000
b1100111 +
1#
#20600000
0#
#20700000
b1101000 +
1#
#20800000
0#
#20900000
b1101001 +
1#
#21000000
0#
#21100000
b1101010 +
1#
#21200000
0#
#21300000
b1101011 +
1#
#21400000
0#
#21500000
b1101100 +
1#
#21600000
0#
#21700000
b1101101 +
1#
#21800000
0#
#21900000
b1101110 +
1#
#22000000
0#
#22100000
b1101111 +
1#
#22200000
0#
#22300000
b1110000 +
1#
#22400000
0#
#22500000
b1110001 +
1#
#22600000
0#
#22700000
b1110010 +
1#
#22800000
0#
#22900000
b1110011 +
1#
#23000000
0#
#23100000
b1110100 +
1#
#23200000
0#
#23300000
b1110101 +
1#
#23400000
0#
#23500000
b1110110 +
1#
#23600000
0#
#23700000
b1110111 +
1#
#23800000
0#
#23900000
b1111000 +
1#
#24000000
0#
#24100000
b1111001 +
1#
#24200000
0#
#24300000
b1111010 +
1#
#24400000
0#
#24500000
b1111011 +
1#
#24600000
0#
#24700000
b1111100 +
1#
#24800000
0#
#24900000
b1111101 +
1#
#25000000
0#
#25100000
b1111110 +
1#
#25200000
0#
#25300000
b1111111 +
1#
#25400000
0#
#25500000
b10000000 +
1#
#25600000
0#
#25700000
b10000001 +
1#
#25800000
0#
#25900000
b10000010 +
1#
#26000000
0#
#26100000
b10000011 +
1#
#26200000
0#
#26300000
b10000100 +
1#
#26400000
0#
#26500000
b10000101 +
1#
#26600000
0#
#26700000
b10000110 +
1#
#26800000
0#
#26900000
b10000111 +
1#
#27000000
0#
#27100000
b10001000 +
1#
#27200000
0#
#27300000
b10001001 +
1#
#27400000
0#
#27500000
b10001010 +
1#
#27600000
0#
#27700000
b10001011 +
1#
#27800000
0#
#27900000
b10001100 +
1#
#28000000
0#
#28100000
b10001101 +
1#
#28200000
0#
#28300000
b10001110 +
1#
#28400000
0#
#28500000
b10001111 +
1#
#28600000
0#
#28700000
b10010000 +
1#
#28800000
0#
#28900000
b10010001 +
1#
#29000000
0#
#29100000
b10010010 +
1#
#29200000
0#
#29300000
b10010011 +
1#
#29400000
0#
#29500000
b10010100 +
1#
#29600000
0#
#29700000
b10010101 +
1#
#29800000
0#
#29900000
b10010110 +
1#
#30000000
0#
#30100000
b10010111 +
1#
#30200000
0#
#30300000
b10011000 +
1#
#30400000
0#
#30500000
b10011001 +
1#
#30600000
0#
#30700000
b10011010 +
1#
#30800000
0#
#30900000
b10011011 +
1#
#31000000
0#
#31100000
b10011100 +
1#
#31200000
0#
#31300000
b10011101 +
1#
#31400000
0#
#31500000
b10011110 +
1#
#31600000
0#
#31700000
b10011111 +
1#
#31800000
0#
#31900000
b10100000 +
1#
#32000000
0#
#32100000
b10100001 +
1#
#32200000
0#
#32300000
b10100010 +
1#
#32400000
0#
#32500000
b10100011 +
1#
#32600000
0#
#32700000
b10100100 +
1#
#32800000
0#
#32900000
b10100101 +
1#
#33000000
0#
#33100000
b10100110 +
1#
#33200000
0#
#33300000
b10100111 +
1#
#33400000
0#
#33500000
b10101000 +
1#
#33600000
0#
#33700000
b10101001 +
1#
#33800000
0#
#33900000
b10101010 +
1#
#34000000
0#
#34100000
b10101011 +
1#
#34200000
0#
#34300000
b10101100 +
1#
#34400000
0#
#34500000
b10101101 +
1#
#34600000
0#
#34700000
b10101110 +
1#
#34800000
0#
#34900000
b10101111 +
1#
#35000000
0#
#35100000
b10110000 +
1#
#35200000
0#
#35300000
b10110001 +
1#
#35400000
0#
#35500000
b10110010 +
1#
#35600000
0#
#35700000
b10110011 +
1#
#35800000
0#
#35900000
b10110100 +
1#
#36000000
0#
#36100000
b10110101 +
1#
#36200000
0#
#36300000
b10110110 +
1#
#36400000
0#
#36500000
b10110111 +
1#
#36600000
0#
#36700000
b10111000 +
1#
#36800000
0#
#36900000
b10111001 +
1#
#37000000
0#
#37100000
b10111010 +
1#
#37200000
0#
#37300000
b10111011 +
1#
#37400000
0#
#37500000
b10111100 +
1#
#37600000
0#
#37700000
b10111101 +
1#
#37800000
0#
#37900000
b10111110 +
1#
#38000000
0#
#38100000
b10111111 +
1#
#38200000
0#
#38300000
b11000000 +
1#
#38400000
0#
#38500000
b11000001 +
1#
#38600000
0#
#38700000
b11000010 +
1#
#38800000
0#
#38900000
b11000011 +
1#
#39000000
0#
#39100000
b11000100 +
1#
#39200000
0#
#39300000
b11000101 +
1#
#39400000
0#
#39500000
b11000110 +
1#
#39600000
0#
#39700000
b11000111 +
1#
#39800000
0#
#39900000
b11001000 +
1#
#40000000
0#
#40100000
b11001001 +
1#
#40200000
0#
#40300000
b11001010 +
1#
#40400000
0#
#40500000
b11001011 +
1#
#40600000
0#
#40700000
b11001100 +
1#
#40800000
0#
#40900000
b11001101 +
1#
#41000000
0#
#41100000
b11001110 +
1#
#41200000
0#
#41300000
b11001111 +
1#
#41400000
0#
#41500000
b11010000 +
1#
#41600000
0#
#41700000
b11010001 +
1#
#41800000
0#
#41900000
b11010010 +
1#
#42000000
0#
#42100000
b11010011 +
1#
#42200000
0#
#42300000
b11010100 +
1#
#42400000
0#
#42500000
b11010101 +
1#
#42600000
0#
#42700000
b11010110 +
1#
#42800000
0#
#42900000
b11010111 +
1#
#43000000
0#
#43100000
b11011000 +
1#
#43200000
0#
#43300000
b11011001 +
1#
#43400000
0#
#43500000
b11011010 +
1#
#43600000
0#
#43700000
b11011011 +
1#
#43800000
0#
#43900000
b11011100 +
1#
#44000000
0#
#44100000
b11011101 +
1#
#44200000
0#
#44300000
b11011110 +
1#
#44400000
0#
#44500000
b11011111 +
1#
#44600000
0#
#44700000
b11100000 +
1#
#44800000
0#
#44900000
b11100001 +
1#
#45000000
0#
#45100000
b11100010 +
1#
#45200000
0#
#45300000
b11100011 +
1#
#45400000
0#
#45500000
b11100100 +
1#
#45600000
0#
#45700000
b11100101 +
1#
#45800000
0#
#45900000
b11100110 +
1#
#46000000
0#
#46100000
b11100111 +
1#
#46200000
0#
#46300000
b11101000 +
1#
#46400000
0#
#46500000
b11101001 +
1#
#46600000
0#
#46700000
b11101010 +
1#
#46800000
0#
#46900000
b11101011 +
1#
#47000000
0#
#47100000
b11101100 +
1#
#47200000
0#
#47300000
b11101101 +
1#
#47400000
0#
#47500000
b11101110 +
1#
#47600000
0#
#47700000
b11101111 +
1#
#47800000
0#
#47900000
b11110000 +
1#
#48000000
0#
#48100000
b11110001 +
1#
#48200000
0#
#48300000
b11110010 +
1#
#48400000
0#
#48500000
b11110011 +
1#
#48600000
0#
#48700000
b11110100 +
1#
#48800000
0#
#48900000
b11110101 +
1#
#49000000
0#
#49100000
b11110110 +
1#
#49200000
0#
#49300000
b11110111 +
1#
#49400000
0#
#49500000
b11111000 +
1#
#49600000
0#
#49700000
b11111001 +
1#
#49800000
0#
#49900000
b11111010 +
1#
#50000000
0#
#50100000
b11111011 +
1#
#50200000
0#
#50300000
b11111100 +
1#
#50400000
0#
#50500000
b11111101 +
1#
#50600000
0#
#50700000
b11111110 +
1#
#50800000
0#
#50900000
b0 +
1#
#51000000
0#
#51100000
b1 +
1#
#51200000
0#
b1 '
b0 $
b0 (
#51300000
b10 +
1#
#51400000
0#
#51500000
b11 +
1#
#51600000
0#
#51700000
b100 +
1#
#51800000
0#
#51900000
b101 +
1#
#52000000
0#
#52100000
b110 +
1#
#52200000
0#
#52300000
b111 +
1#
#52400000
0#
#52500000
b1000 +
1#
#52600000
0#
#52700000
b1001 +
1#
#52800000
0#
#52900000
b1010 +
1#
#53000000
0#
#53100000
b1011 +
1#
#53200000
0#
#53300000
b1100 +
1#
#53400000
0#
#53500000
b1101 +
1#
#53600000
0#
#53700000
b1110 +
1#
#53800000
0#
#53900000
b1111 +
1#
#54000000
0#
#54100000
b10000 +
1#
#54200000
0#
#54300000
b10001 +
1#
#54400000
0#
#54500000
b10010 +
1#
#54600000
0#
#54700000
b10011 +
1#
#54800000
0#
#54900000
b10100 +
1#
#55000000
0#
#55100000
b10101 +
1#
#55200000
0#
#55300000
b10110 +
1#
#55400000
0#
#55500000
b10111 +
1#
#55600000
0#
#55700000
b11000 +
1#
#55800000
0#
#55900000
b11001 +
1#
#56000000
0#
#56100000
b11010 +
1#
#56200000
0#
#56300000
b11011 +
1#
#56400000
0#
#56500000
b11100 +
1#
#56600000
0#
#56700000
b11101 +
1#
#56800000
0#
#56900000
b11110 +
1#
#57000000
0#
#57100000
b11111 +
1#
#57200000
0#
#57300000
b100000 +
1#
#57400000
0#
#57500000
b100001 +
1#
#57600000
0#
#57700000
b100010 +
1#
#57800000
0#
#57900000
b100011 +
1#
#58000000
0#
#58100000
b100100 +
1#
#58200000
0#
#58300000
b100101 +
1#
#58400000
0#
#58500000
b100110 +
1#
#58600000
0#
#58700000
b100111 +
1#
#58800000
0#
#58900000
b101000 +
1#
#59000000
0#
#59100000
b101001 +
1#
#59200000
0#
#59300000
b101010 +
1#
#59400000
0#
#59500000
b101011 +
1#
#59600000
0#
#59700000
b101100 +
1#
#59800000
0#
#59900000
b101101 +
1#
#60000000
0#
#60100000
b101110 +
1#
#60200000
0#
#60300000
b101111 +
1#
#60400000
0#
#60500000
b110000 +
1#
#60600000
0#
#60700000
b110001 +
1#
#60800000
0#
#60900000
b110010 +
1#
#61000000
0#
#61100000
b110011 +
1#
#61200000
0#
#61300000
b110100 +
1#
#61400000
0#
#61500000
b110101 +
1#
#61600000
0#
#61700000
b110110 +
1#
#61800000
0#
#61900000
b110111 +
1#
#62000000
0#
#62100000
b111000 +
1#
#62200000
0#
#62300000
b111001 +
1#
#62400000
0#
#62500000
b111010 +
1#
#62600000
0#
#62700000
b111011 +
1#
#62800000
0#
#62900000
b111100 +
1#
#63000000
0#
#63100000
b111101 +
1#
#63200000
0#
#63300000
b111110 +
1#
#63400000
0#
#63500000
b111111 +
1#
#63600000
0#
#63700000
b1000000 +
1#
#63800000
0#
#63900000
b1000001 +
1#
#64000000
0#
#64100000
b1000010 +
1#
#64200000
0#
#64300000
b1000011 +
1#
#64400000
0#
#64500000
b1000100 +
1#
#64600000
0#
#64700000
b1000101 +
1#
#64800000
0#
#64900000
b1000110 +
1#
#65000000
0#
#65100000
b1000111 +
1#
#65200000
0#
#65300000
b1001000 +
1#
#65400000
0#
#65500000
b1001001 +
1#
#65600000
0#
#65700000
b1001010 +
1#
#65800000
0#
#65900000
b1001011 +
1#
#66000000
0#
#66100000
b1001100 +
1#
#66200000
0#
#66300000
b1001101 +
1#
#66400000
0#
#66500000
b1001110 +
1#
#66600000
0#
#66700000
b1001111 +
1#
#66800000
0#
#66900000
b1010000 +
1#
#67000000
0#
#67100000
b1010001 +
1#
#67200000
0#
#67300000
b1010010 +
1#
#67400000
0#
#67500000
b1010011 +
1#
#67600000
0#
#67700000
b1010100 +
1#
#67800000
0#
#67900000
b1010101 +
1#
#68000000
0#
#68100000
b1010110 +
1#
#68200000
0#
#68300000
b1010111 +
1#
#68400000
0#
#68500000
b1011000 +
1#
#68600000
0#
#68700000
b1011001 +
1#
#68800000
0#
#68900000
b1011010 +
1#
#69000000
0#
#69100000
b1011011 +
1#
#69200000
0#
#69300000
b1011100 +
1#
#69400000
0#
#69500000
b1011101 +
1#
#69600000
0#
#69700000
b1011110 +
1#
#69800000
0#
#69900000
b1011111 +
1#
#70000000
0#
#70100000
b1100000 +
1#
#70200000
0#
#70300000
b1100001 +
1#
#70400000
0#
#70500000
b1100010 +
1#
#70600000
0#
#70700000
b1100011 +
1#
#70800000
0#
#70900000
b1100100 +
1#
#71000000
0#
#71100000
b1100101 +
1#
#71200000
0#
#71300000
b1100110 +
1#
#71400000
0#
#71500000
b1100111 +
1#
#71600000
0#
#71700000
b1101000 +
1#
#71800000
0#
#71900000
b1101001 +
1#
#72000000
0#
#72100000
b1101010 +
1#
#72200000
0#
#72300000
b1101011 +
1#
#72400000
0#
#72500000
b1101100 +
1#
#72600000
0#
#72700000
b1101101 +
1#
#72800000
0#
#72900000
b1101110 +
1#
#73000000
0#
#73100000
b1101111 +
1#
#73200000
0#
#73300000
b1110000 +
1#
#73400000
0#
#73500000
b1110001 +
1#
#73600000
0#
#73700000
b1110010 +
1#
#73800000
0#
#73900000
b1110011 +
1#
#74000000
0#
#74100000
b1110100 +
1#
#74200000
0#
#74300000
b1110101 +
1#
#74400000
0#
#74500000
b1110110 +
1#
#74600000
0#
#74700000
b1110111 +
1#
#74800000
0#
#74900000
b1111000 +
1#
#75000000
0#
#75100000
b1111001 +
1#
#75200000
0#
#75300000
b1111010 +
1#
#75400000
0#
#75500000
b1111011 +
1#
#75600000
0#
#75700000
b1111100 +
1#
#75800000
0#
#75900000
b1111101 +
1#
#76000000
0#
#76100000
b1111110 +
1#
#76200000
0#
#76300000
b1111111 +
1#
#76400000
0#
#76500000
b10000000 +
1#
#76600000
0#
#76700000
b10000001 +
1#
#76800000
0#
#76900000
b10000010 +
1#
#77000000
0#
#77100000
b10000011 +
1#
#77200000
0#
#77300000
b10000100 +
1#
#77400000
0#
#77500000
b10000101 +
1#
#77600000
0#
#77700000
b10000110 +
1#
#77800000
0#
#77900000
b10000111 +
1#
#78000000
0#
#78100000
b10001000 +
1#
#78200000
0#
#78300000
b10001001 +
1#
#78400000
0#
#78500000
b10001010 +
1#
#78600000
0#
#78700000
b10001011 +
1#
#78800000
0#
#78900000
b10001100 +
1#
#79000000
0#
#79100000
b10001101 +
1#
#79200000
0#
#79300000
b10001110 +
1#
#79400000
0#
#79500000
b10001111 +
1#
#79600000
0#
#79700000
b10010000 +
1#
#79800000
0#
#79900000
b10010001 +
1#
#80000000
0#
#80100000
b10010010 +
1#
#80200000
0#
#80300000
b10010011 +
1#
#80400000
0#
#80500000
b10010100 +
1#
#80600000
0#
#80700000
b10010101 +
1#
#80800000
0#
#80900000
b10010110 +
1#
#81000000
0#
#81100000
b10010111 +
1#
#81200000
0#
#81300000
b10011000 +
1#
#81400000
0#
#81500000
b10011001 +
1#
#81600000
0#
#81700000
b10011010 +
1#
#81800000
0#
#81900000
b10011011 +
1#
#82000000
0#
#82100000
b10011100 +
1#
#82200000
0#
#82300000
b10011101 +
1#
#82400000
0#
#82500000
b10011110 +
1#
#82600000
0#
#82700000
b10011111 +
1#
#82800000
0#
#82900000
b10100000 +
1#
#83000000
0#
#83100000
b10100001 +
1#
#83200000
0#
#83300000
b10100010 +
1#
#83400000
0#
#83500000
b10100011 +
1#
#83600000
0#
#83700000
b10100100 +
1#
#83800000
0#
#83900000
b10100101 +
1#
#84000000
0#
#84100000
b10100110 +
1#
#84200000
0#
#84300000
b10100111 +
1#
#84400000
0#
#84500000
b10101000 +
1#
#84600000
0#
#84700000
b10101001 +
1#
#84800000
0#
#84900000
b10101010 +
1#
#85000000
0#
#85100000
b10101011 +
1#
#85200000
0#
#85300000
b10101100 +
1#
#85400000
0#
#85500000
b10101101 +
1#
#85600000
0#
#85700000
b10101110 +
1#
#85800000
0#
#85900000
b10101111 +
1#
#86000000
0#
#86100000
b10110000 +
1#
#86200000
0#
#86300000
b10110001 +
1#
#86400000
0#
#86500000
b10110010 +
1#
#86600000
0#
#86700000
b10110011 +
1#
#86800000
0#
#86900000
b10110100 +
1#
#87000000
0#
#87100000
b10110101 +
1#
#87200000
0#
#87300000
b10110110 +
1#
#87400000
0#
#87500000
b10110111 +
1#
#87600000
0#
#87700000
b10111000 +
1#
#87800000
0#
#87900000
b10111001 +
1#
#88000000
0#
#88100000
b10111010 +
1#
#88200000
0#
#88300000
b10111011 +
1#
#88400000
0#
#88500000
b10111100 +
1#
#88600000
0#
#88700000
b10111101 +
1#
#88800000
0#
#88900000
b10111110 +
1#
#89000000
0#
#89100000
b10111111 +
1#
#89200000
0#
#89300000
b11000000 +
1#
#89400000
0#
#89500000
b11000001 +
1#
#89600000
0#
#89700000
b11000010 +
1#
#89800000
0#
#89900000
b11000011 +
1#
#90000000
0#
#90100000
b11000100 +
1#
#90200000
0#
#90300000
b11000101 +
1#
#90400000
0#
#90500000
b11000110 +
1#
#90600000
0#
#90700000
b11000111 +
1#
#90800000
0#
#90900000
b11001000 +
1#
#91000000
0#
#91100000
b11001001 +
1#
#91200000
0#
#91300000
b11001010 +
1#
#91400000
0#
#91500000
b11001011 +
1#
#91600000
0#
#91700000
b11001100 +
1#
#91800000
0#
#91900000
b11001101 +
1#
#92000000
0#
#92100000
b11001110 +
1#
#92200000
0#
#92300000
b11001111 +
1#
#92400000
0#
#92500000
b11010000 +
1#
#92600000
0#
#92700000
b11010001 +
1#
#92800000
0#
#92900000
b11010010 +
1#
#93000000
0#
#93100000
b11010011 +
1#
#93200000
0#
#93300000
b11010100 +
1#
#93400000
0#
#93500000
b11010101 +
1#
#93600000
0#
#93700000
b11010110 +
1#
#93800000
0#
#93900000
b11010111 +
1#
#94000000
0#
#94100000
b11011000 +
1#
#94200000
0#
#94300000
b11011001 +
1#
#94400000
0#
#94500000
b11011010 +
1#
#94600000
0#
#94700000
b11011011 +
1#
#94800000
0#
#94900000
b11011100 +
1#
#95000000
0#
#95100000
b11011101 +
1#
#95200000
0#
#95300000
b11011110 +
1#
#95400000
0#
#95500000
b11011111 +
1#
#95600000
0#
#95700000
b11100000 +
1#
#95800000
0#
#95900000
b11100001 +
1#
#96000000
0#
#96100000
b11100010 +
1#
#96200000
0#
#96300000
b11100011 +
1#
#96400000
0#
#96500000
b11100100 +
1#
#96600000
0#
#96700000
b11100101 +
1#
#96800000
0#
#96900000
b11100110 +
1#
#97000000
0#
#97100000
b11100111 +
1#
#97200000
0#
#97300000
b11101000 +
1#
#97400000
0#
#97500000
b11101001 +
1#
#97600000
0#
#97700000
b11101010 +
1#
#97800000
0#
#97900000
b11101011 +
1#
#98000000
0#
#98100000
b11101100 +
1#
#98200000
0#
#98300000
b11101101 +
1#
#98400000
0#
#98500000
b11101110 +
1#
#98600000
0#
#98700000
b11101111 +
1#
#98800000
0#
#98900000
b11110000 +
1#
#99000000
0#
#99100000
b11110001 +
1#
#99200000
0#
#99300000
b11110010 +
1#
#99400000
0#
#99500000
b11110011 +
1#
#99600000
0#
#99700000
b11110100 +
1#
#99800000
0#
#99900000
b11110101 +
1#
#100000000
0#
#100100000
b11110110 +
1#
#100200000
0#
#100300000
b11110111 +
1#
#100400000
0#
#100500000
b11111000 +
1#
#100600000
0#
#100700000
b11111001 +
1#
#100800000
0#
#100900000
b11111010 +
1#
#101000000
0#
#101100000
b11111011 +
1#
#101200000
0#
#101300000
b11111100 +
1#
#101400000
0#
#101500000
b11111101 +
1#
#101600000
0#
#101700000
b11111110 +
1#
#101800000
0#
#101900000
b0 +
1#
#102000000
0#
#102100000
b1 +
1#
#102200000
0#
#102300000
b10 +
1#
#102400000
0#
b10 '
b1 $
b1 (
#102500000
b11 +
1#
#102600000
0#
#102700000
b100 +
1#
#102800000
0#
#102900000
b101 +
1#
#103000000
0#
#103100000
b110 +
1#
#103200000
0#
#103300000
b111 +
1#
#103400000
0#
#103500000
b1000 +
1#
#103600000
0#
#103700000
b1001 +
1#
#103800000
0#
#103900000
b1010 +
1#
#104000000
0#
#104100000
b1011 +
1#
#104200000
0#
#104300000
b1100 +
1#
#104400000
0#
#104500000
b1101 +
1#
#104600000
0#
#104700000
b1110 +
1#
#104800000
0#
#104900000
b1111 +
1#
#105000000
0#
#105100000
b10000 +
1#
#105200000
0#
#105300000
b10001 +
1#
#105400000
0#
#105500000
b10010 +
1#
#105600000
0#
#105700000
b10011 +
1#
#105800000
0#
#105900000
b10100 +
1#
#106000000
0#
#106100000
b10101 +
1#
#106200000
0#
#106300000
b10110 +
1#
#106400000
0#
#106500000
b10111 +
1#
#106600000
0#
#106700000
b11000 +
1#
#106800000
0#
#106900000
b11001 +
1#
#107000000
0#
#107100000
b11010 +
1#
#107200000
0#
#107300000
b11011 +
1#
#107400000
0#
#107500000
b11100 +
1#
#107600000
0#
#107700000
b11101 +
1#
#107800000
0#
#107900000
b11110 +
1#
#108000000
0#
#108100000
b11111 +
1#
#108200000
0#
#108300000
b100000 +
1#
#108400000
0#
#108500000
b100001 +
1#
#108600000
0#
#108700000
b100010 +
1#
#108800000
0#
#108900000
b100011 +
1#
#109000000
0#
#109100000
b100100 +
1#
#109200000
0#
#109300000
b100101 +
1#
#109400000
0#
#109500000
b100110 +
1#
#109600000
0#
#109700000
b100111 +
1#
#109800000
0#
#109900000
b101000 +
1#
#110000000
0#
#110100000
b101001 +
1#
#110200000
0#
#110300000
b101010 +
1#
#110400000
0#
#110500000
b101011 +
1#
#110600000
0#
#110700000
b101100 +
1#
#110800000
0#
#110900000
b101101 +
1#
#111000000
0#
#111100000
b101110 +
1#
#111200000
0#
#111300000
b101111 +
1#
#111400000
0#
#111500000
b110000 +
1#
#111600000
0#
#111700000
b110001 +
1#
#111800000
0#
#111900000
b110010 +
1#
#112000000
0#
#112100000
b110011 +
1#
#112200000
0#
#112300000
b110100 +
1#
#112400000
0#
#112500000
b110101 +
1#
#112600000
0#
#112700000
b110110 +
1#
#112800000
0#
#112900000
b110111 +
1#
#113000000
0#
#113100000
b111000 +
1#
#113200000
0#
#113300000
b111001 +
1#
#113400000
0#
#113500000
b111010 +
1#
#113600000
0#
#113700000
b111011 +
1#
#113800000
0#
#113900000
b111100 +
1#
#114000000
0#
#114100000
b111101 +
1#
#114200000
0#
#114300000
b111110 +
1#
#114400000
0#
#114500000
b111111 +
1#
#114600000
0#
#114700000
b1000000 +
1#
#114800000
0#
#114900000
b1000001 +
1#
#115000000
0#
#115100000
b1000010 +
1#
#115200000
0#
#115300000
b1000011 +
1#
#115400000
0#
#115500000
b1000100 +
1#
#115600000
0#
#115700000
b1000101 +
1#
#115800000
0#
#115900000
b1000110 +
1#
#116000000
0#
#116100000
b1000111 +
1#
#116200000
0#
#116300000
b1001000 +
1#
#116400000
0#
#116500000
b1001001 +
1#
#116600000
0#
#116700000
b1001010 +
1#
#116800000
0#
#116900000
b1001011 +
1#
#117000000
0#
#117100000
b1001100 +
1#
#117200000
0#
#117300000
b1001101 +
1#
#117400000
0#
#117500000
b1001110 +
1#
#117600000
0#
#117700000
b1001111 +
1#
#117800000
0#
#117900000
b1010000 +
1#
#118000000
0#
#118100000
b1010001 +
1#
#118200000
0#
#118300000
b1010010 +
1#
#118400000
0#
#118500000
b1010011 +
1#
#118600000
0#
#118700000
b1010100 +
1#
#118800000
0#
#118900000
b1010101 +
1#
#119000000
0#
#119100000
b1010110 +
1#
#119200000
0#
#119300000
b1010111 +
1#
#119400000
0#
#119500000
b1011000 +
1#
#119600000
0#
#119700000
b1011001 +
1#
#119800000
0#
#119900000
b1011010 +
1#
#120000000
0#
#120100000
b1011011 +
1#
#120200000
0#
#120300000
b1011100 +
1#
#120400000
0#
#120500000
b1011101 +
1#
#120600000
0#
#120700000
b1011110 +
1#
#120800000
0#
#120900000
b1011111 +
1#
#121000000
0#
#121100000
b1100000 +
1#
#121200000
0#
#121300000
b1100001 +
1#
#121400000
0#
#121500000
b1100010 +
1#
#121600000
0#
#121700000
b1100011 +
1#
#121800000
0#
#121900000
b1100100 +
1#
#122000000
0#
#122100000
b1100101 +
1#
#122200000
0#
#122300000
b1100110 +
1#
#122400000
0#
#122500000
b1100111 +
1#
#122600000
0#
#122700000
b1101000 +
1#
#122800000
0#
#122900000
b1101001 +
1#
#123000000
0#
#123100000
b1101010 +
1#
#123200000
0#
