Calculator_Pipeline/Arithmetic_Logic_Unit.v
module Arithmetic_Logic_Unit #(
    parameter DATA_WIDTH = 18
) (
    input [1 : 0] Operation,
    input [7 : 0] Operand_1,
    input [7 : 0] Operand_2,

    output reg [DATA_WIDTH - 1 : 0] Result
);
    always @(*)
        begin
        case (Operation)
            2'b00 : Result = Operand_1 + Operand_2;
            2'b01 : Result = Operand_1 - Operand_2;
            2'b10 : Result = Operand_1 * Operand_2;
            2'b11 : Result = Operand_1 / Operand_2;
        endcase
    end
endmodule

Calculator_Pipeline/Control_Unit.v
module Control_Unit (
    input [17 : 0] Instruction,

    output [1 : 0] Operation,
    output [7 : 0] Operand_1,
    output [7 : 0] Operand_2
);
    
    assign Operation = Instruction[17 : 16];
    assign Operand_1 = Instruction[15 : 8];
    assign Operand_2 = Instruction[7 : 0];
endmodule

Calculator_Pipeline/Instruction_Memory.v
module Instruction_Memory #(
    parameter ADDRESS_WIDTH = 20,
    parameter DATA_WIDTH = 32
) (
    input Enable,
    input [ADDRESS_WIDTH - 1 : 0] Address,

    output [DATA_WIDTH - 1 : 0] Data
);

    reg [DATA_WIDTH - 1 : 0] Memory [$pow(2, ADDRESS_WIDTH) - 1 : 0];

    initial
    begin
		Memory[0]	=	32'h4e583111;
		Memory[1]	=	32'h49c30922;
		Memory[2]	=	32'h42beee82;
		Memory[3]	=	32'he9406ab1;
		Memory[4]	=	32'h80a545c5;
		Memory[5]	=	32'h9bd8d943;
		Memory[6]	=	32'h99f4ffb7;
		Memory[7]	=	32'hf325f246;
		Memory[8]	=	32'h6e8da1ce;
		Memory[9]	=	32'h1be20f9f;
		Memory[10]	=	32'h992c5e1b;
		Memory[11]	=	32'h419f421b;
		Memory[12]	=	32'h64c0bfba;
		Memory[13]	=	32'h8234b878;
		Memory[14]	=	32'h49aa8b3f;
		Memory[15]	=	32'h82d865c1;
		Memory[16]	=	32'hce61e8c1;
		Memory[17]	=	32'h93594ba0;
		Memory[18]	=	32'h508f936;
		Memory[19]	=	32'hb088ced6;
		Memory[20]	=	32'hb2ba6cd5;
		Memory[21]	=	32'h6b069ff;
		Memory[22]	=	32'hf23f005f;
		Memory[23]	=	32'h9adec517;
		Memory[24]	=	32'hfdaf238;
		Memory[25]	=	32'h64d4dcb2;
		Memory[26]	=	32'hb6790da2;
		Memory[27]	=	32'hbe423970;
		Memory[28]	=	32'h415ac756;
		Memory[29]	=	32'hbb79e6ed;
		Memory[30]	=	32'hd2c08fe2;
		Memory[31]	=	32'h3eec7c09;
		Memory[32]	=	32'h6033af0;
		Memory[33]	=	32'h529583a6;
		Memory[34]	=	32'h27c28045;
		Memory[35]	=	32'hf6862995;
		Memory[36]	=	32'h29e39259;
		Memory[37]	=	32'h3e8fe397;
		Memory[38]	=	32'h745c53d3;
		Memory[39]	=	32'h5b319790;
		Memory[40]	=	32'h5811ceb8;
		Memory[41]	=	32'hd51c9c3;
		Memory[42]	=	32'h25d3905c;
		Memory[43]	=	32'h4576208d;
		Memory[44]	=	32'h8e22de38;
		Memory[45]	=	32'he3d75f02;
		Memory[46]	=	32'h5cc6bbef;
		Memory[47]	=	32'ha4311f45;
		Memory[48]	=	32'h18984958;
		Memory[49]	=	32'h58afe0c;
		Memory[50]	=	32'h61d6f5e8;
		Memory[51]	=	32'h9ff9c796;
		Memory[52]	=	32'h698e5431;
		Memory[53]	=	32'hc3c726e;
		Memory[54]	=	32'h7ec48a8e;
		Memory[55]	=	32'h51f8ca32;
		Memory[56]	=	32'hff5cc0d4;
		Memory[57]	=	32'hee76dfeb;
		Memory[58]	=	32'hbf1b8463;
		Memory[59]	=	32'h3054651e;
		Memory[60]	=	32'h73f961c9;
		Memory[61]	=	32'h26b19349;
		Memory[62]	=	32'hba1b5043;
		Memory[63]	=	32'hbe18d8db;
		Memory[64]	=	32'h213f2395;
		Memory[65]	=	32'h7a8b5336;
		Memory[66]	=	32'hb552f1a;
		Memory[67]	=	32'h746c335b;
		Memory[68]	=	32'h9a86a55a;
		Memory[69]	=	32'h1cb50242;
		Memory[70]	=	32'hef54aae8;
		Memory[71]	=	32'heaffdea0;
		Memory[72]	=	32'h17f1327e;
		Memory[73]	=	32'hcce54048;
		Memory[74]	=	32'h8b023acb;
		Memory[75]	=	32'hbd99d40c;
		Memory[76]	=	32'ha4621ee0;
		Memory[77]	=	32'hd522cb08;
		Memory[78]	=	32'h409a283c;
		Memory[79]	=	32'h8cf11655;
		Memory[80]	=	32'h83440f4e;
		Memory[81]	=	32'he0737a40;
		Memory[82]	=	32'he4aaf8bb;
		Memory[83]	=	32'hc0fef5e6;
		Memory[84]	=	32'h45ce770;
		Memory[85]	=	32'he45410f5;
		Memory[86]	=	32'h1bb569d9;
		Memory[87]	=	32'h8d771f;
		Memory[88]	=	32'hf49870cd;
		Memory[89]	=	32'h6365464e;
		Memory[90]	=	32'hf3f72df8;
		Memory[91]	=	32'h375bd03d;
		Memory[92]	=	32'h43d70239;
		Memory[93]	=	32'h62f03d6a;
		Memory[94]	=	32'hbbb1019f;
		Memory[95]	=	32'h9bab63a1;
		Memory[96]	=	32'h7138f258;
		Memory[97]	=	32'ha0a621b0;
		Memory[98]	=	32'hb7043507;
		Memory[99]	=	32'hc118244c;
    end

    assign Data = Enable ? Memory[Address] : 'bz;
endmodule

Calculator_Pipeline/Core.v
`include "Instruction_Memory.v"
`include "Control_Unit.v"
`include "Arithmetic_Logic_Unit.v"

module Core #(
    parameter ADDRESS_WIDTH = 10,
    parameter DATA_WIDTH = 18
) (
    input CLK,
    input [ADDRESS_WIDTH - 1 : 0] Counter,
    output [DATA_WIDTH - 1 : 0] Result
);
    reg [ADDRESS_WIDTH - 1 : 0] Address;

    wire    [DATA_WIDTH - 1 : 0] Instruction_S0;
    reg     [DATA_WIDTH - 1 : 0] Instruction_S1;

    wire    [1 : 0] Operation_S1;
    reg     [1 : 0] Operation_S2;

    wire    [7 : 0] Operand_1_S1;
    reg     [7 : 0] Operand_1_S2;

    wire    [7 : 0] Operand_2_S1;
    reg     [7 : 0] Operand_2_S2;

    Instruction_Memory #(ADDRESS_WIDTH, DATA_WIDTH)  Imem (
        .Enable(1'b1),
        .Address(Address),
        .Data(Instruction_S0)
    );

    Control_Unit control_unit (
        .Instruction(Instruction_S1),
        .Operation(Operation_S1),
        .Operand_1(Operand_1_S1),
        .Operand_2(Operand_2_S1)
    );

    Arithmetic_Logic_Unit #(DATA_WIDTH) ALU (
        .Operation(Operation_S2),
        .Operand_1(Operand_1_S2),
        .Operand_2(Operand_2_S2),

        .Result(Result)
    );

    always @(posedge CLK) 
        Address <= Counter;
    always @(posedge CLK) 
        Instruction_S1 <= Instruction_S0;
    always @(posedge CLK)
    begin
        Operation_S2 <= Operation_S1;
        Operand_1_S2 <= Operand_1_S1;
        Operand_2_S2 <= Operand_2_S1;
    end
endmodule

Calculator_Pipeline/Core_TB.v
`timescale 1ns/1ns

`include "Core.v"

module Core_TB;
    parameter State = 1;  // Sequential : 3 -- Pipline : 1
    parameter ADDRESS_WIDTH = 10;
    parameter DATA_WIDTH = 18;

    reg CLK = 0;
    parameter T = 2;
    always #(T / 2)  CLK = ~CLK;

    reg [ADDRESS_WIDTH - 1 : 0] Counter;
    wire [DATA_WIDTH - 1 : 0] Result;

    Core #(ADDRESS_WIDTH, DATA_WIDTH) uut (CLK, Counter, Result);

    initial
    begin
        $dumpfile("Core.vcd");
        $dumpvars(0, Core_TB);

        for (integer i = 0; i < 100; i = i + 1)
        begin
            Counter = i;
            #(T * State);           
        end
        $finish;
    end
endmodule

Calculator_Pipeline/Core.vcd
$date
	Thu Apr 20 20:37:48 2023
$end
$version
	Icarus Verilog
$end
$timescale
	1ns
$end
$scope module Core_TB $end
$var wire 18 ! Result [17:0] $end
$var parameter 32 " ADDRESS_WIDTH $end
$var parameter 32 # DATA_WIDTH $end
$var parameter 32 $ State $end
$var parameter 32 % T $end
$var reg 1 & CLK $end
$var reg 10 ' Counter [9:0] $end
$scope module uut $end
$var wire 1 & CLK $end
$var wire 10 ( Counter [9:0] $end
$var wire 18 ) Result [17:0] $end
$var wire 2 * Operation_S1 [1:0] $end
$var wire 8 + Operand_2_S1 [7:0] $end
$var wire 8 , Operand_1_S1 [7:0] $end
$var wire 18 - Instruction_S0 [17:0] $end
$var parameter 32 . ADDRESS_WIDTH $end
$var parameter 32 / DATA_WIDTH $end
$var reg 10 0 Address [9:0] $end
$var reg 18 1 Instruction_S1 [17:0] $end
$var reg 8 2 Operand_1_S2 [7:0] $end
$var reg 8 3 Operand_2_S2 [7:0] $end
$var reg 2 4 Operation_S2 [1:0] $end
$scope module ALU $end
$var wire 8 5 Operand_1 [7:0] $end
$var wire 8 6 Operand_2 [7:0] $end
$var wire 2 7 Operation [1:0] $end
$var parameter 32 8 DATA_WIDTH $end
$var reg 18 9 Result [17:0] $end
$upscope $end
$scope module Imem $end
$var wire 10 : Address [9:0] $end
$var wire 18 ; Data [17:0] $end
$var wire 1 < Enable $end
$var parameter 32 = ADDRESS_WIDTH $end
$var parameter 32 > DATA_WIDTH $end
$upscope $end
$scope module control_unit $end
$var wire 18 ? Instruction [17:0] $end
$var wire 2 @ Operation [1:0] $end
$var wire 8 A Operand_2 [7:0] $end
$var wire 8 B Operand_1 [7:0] $end
$upscope $end
$upscope $end
$scope begin $ivl_for_loop0 $end
$var integer 32 C i [31:0] $end
$upscope $end
$upscope $end
$enddefinitions $end
$comment Show the parameter values. $end
$dumpall
b10010 >
b1010 =
b10010 8
b10010 /
b1010 .
b10 %
b1 $
b10010 #
b1010 "
$end
#0
$dumpvars
b0 C
bx B
bx A
bx @
bx ?
1<
bx ;
bx :
bx 9
bx 7
bx 6
bx 5
bx 4
bx 3
bx 2
bx 1
bx 0
bx -
bx ,
bx +
bx *
bx )
b0 (
b0 '
0&
bx !
$end
#1
b11000100010001 -
b11000100010001 ;
b0 0
b0 :
1&
#2
0&
b1 '
b1 (
b1 C
#3
b0 *
b0 @
b110001 ,
b110001 B
b10001 +
b10001 A
b11000100010001 1
b11000100010001 ?
b110000100100100010 -
b110000100100100010 ;
b1 0
b1 :
1&
#4
0&
b10 '
b10 (
b10 C
#5
b11 *
b11 @
b1001 ,
b1001 B
b100010 +
b100010 A
b1000010 !
b1000010 )
b1000010 9
b101110111010000010 -
b101110111010000010 ;
b10 0
b10 :
b110000100100100010 1
b110000100100100010 ?
b10001 3
b10001 6
b110001 2
b110001 5
b0 4
b0 7
1&
#6
0&
b11 '
b11 (
b11 C
#7
b0 !
b0 )
b0 9
b10 *
b10 @
b11101110 ,
b11101110 B
b10000010 +
b10000010 A
b100010 3
b100010 6
b1001 2
b1001 5
b11 4
b11 7
b101110111010000010 1
b101110111010000010 ?
b110101010110001 -
b110101010110001 ;
b11 0
b11 :
1&
#8
0&
b100 '
b100 (
b100 C
#9
b0 *
b0 @
b1101010 ,
b1101010 B
b10110001 +
b10110001 A
b111100011011100 !
b111100011011100 )
b111100011011100 9
b10100010111000101 -
b10100010111000101 ;
b100 0
b100 :
b110101010110001 1
b110101010110001 ?
b10000010 3
b10000010 6
b11101110 2
b11101110 5
b10 4
b10 7
1&
#10
0&
b101 '
b101 (
b101 C
#11
b100011011 !
b100011011 )
b100011011 9
b1 *
b1 @
b1000101 ,
b1000101 B
b11000101 +
b11000101 A
b10110001 3
b10110001 6
b1101010 2
b1101010 5
b0 4
b0 7
b10100010111000101 1
b10100010111000101 ?
b1101100101000011 -
b1101100101000011 ;
b101 0
b101 :
1&
#12
0&
b110 '
b110 (
b110 C
#13
b0 *
b0 @
b11011001 ,
b11011001 B
b1000011 +
b1000011 A
b111111111110000000 !
b111111111110000000 )
b111111111110000000 9
b1111111110110111 -
b1111111110110111 ;
b110 0
b110 :
b1101100101000011 1
b1101100101000011 ?
b11000101 3
b11000101 6
b1000101 2
b1000101 5
b1 4
b1 7
1&
#14
0&
b111 '
b111 (
b111 C
#15
b100011100 !
b100011100 )
b100011100 9
b11111111 ,
b11111111 B
b10110111 +
b10110111 A
b1000011 3
b1000011 6
b11011001 2
b11011001 5
b0 4
b0 7
b1111111110110111 1
b1111111110110111 ?
b11111001001000110 -
b11111001001000110 ;
b111 0
b111 :
1&
#16
0&
b1000 '
b1000 (
b1000 C
#17
b1 *
b1 @
b11110010 ,
b11110010 B
b1000110 +
b1000110 A
b110110110 !
b110110110 )
b110110110 9
b11010000111001110 -
b11010000111001110 ;
b1000 0
b1000 :
b11111001001000110 1
b11111001001000110 ?
b10110111 3
b10110111 6
b11111111 2
b11111111 5
1&
#18
0&
b1001 '
b1001 (
b1001 C
#19
b10101100 !
b10101100 )
b10101100 9
b10100001 ,
b10100001 B
b11001110 +
b11001110 A
b1000110 3
b1000110 6
b11110010 2
b11110010 5
b1 4
b1 7
b11010000111001110 1
b11010000111001110 ?
b100000111110011111 -
b100000111110011111 ;
b1001 0
b1001 :
1&
#20
0&
b1010 '
b1010 (
b1010 C
#21
b10 *
b10 @
b1111 ,
b1111 B
b10011111 +
b10011111 A
b111111111111010011 !
b111111111111010011 )
b111111111111010011 9
b101111000011011 -
b101111000011011 ;
b1010 0
b1010 :
b100000111110011111 1
b100000111110011111 ?
b11001110 3
b11001110 6
b10100001 2
b10100001 5
1&
#22
0&
b1011 '
b1011 (
b1011 C
#23
b100101010001 !
b100101010001 )
b100101010001 9
b0 *
b0 @
b1011110 ,
b1011110 B
b11011 +
b11011 A
b10011111 3
b10011111 6
b1111 2
b1111 5
b10 4
b10 7
b101111000011011 1
b101111000011011 ?
b110100001000011011 -
b110100001000011011 ;
b1011 0
b1011 :
1&
#24
0&
b1100 '
b1100 (
b1100 C
#25
b11 *
b11 @
b1000010 ,
b1000010 B
b1111001 !
b1111001 )
b1111001 9
b1011111110111010 -
b1011111110111010 ;
b1100 0
b1100 :
b110100001000011011 1
b110100001000011011 ?
b11011 3
b11011 6
b1011110 2
b1011110 5
b0 4
b0 7
1&
#26
0&
b1101 '
b1101 (
b1101 C
#27
b10 !
b10 )
b10 9
b0 *
b0 @
b10111111 ,
b10111111 B
b10111010 +
b10111010 A
b1000010 2
b1000010 5
b11 4
b11 7
b1011111110111010 1
b1011111110111010 ?
b1011100001111000 -
b1011100001111000 ;
b1101 0
b1101 :
1&
#28
0&
b1110 '
b1110 (
b1110 C
#29
b10111000 ,
b10111000 B
b1111000 +
b1111000 A
b101111001 !
b101111001 )
b101111001 9
b101000101100111111 -
b101000101100111111 ;
b1110 0
b1110 :
b1011100001111000 1
b1011100001111000 ?
b10111010 3
b10111010 6
b10111111 2
b10111111 5
b0 4
b0 7
1&
#30
0&
b1111 '
b1111 (
b1111 C
#31
b100110000 !
b100110000 )
b100110000 9
b10 *
b10 @
b10001011 ,
b10001011 B
b111111 +
b111111 A
b1111000 3
b1111000 6
b10111000 2
b10111000 5
b101000101100111111 1
b101000101100111111 ?
b110010111000001 -
b110010111000001 ;
b1111 0
b1111 :
1&
#32
0&
b10000 '
b10000 (
b10000 C
#33
b0 *
b0 @
b1100101 ,
b1100101 B
b11000001 +
b11000001 A
b10001000110101 !
b10001000110101 )
b10001000110101 9
b11110100011000001 -
b11110100011000001 ;
b10000 0
b10000 :
b110010111000001 1
b110010111000001 ?
b111111 3
b111111 6
b10001011 2
b10001011 5
b10 4
b10 7
1&
#34
0&
b10001 '
b10001 (
b10001 C
#35
b100100110 !
b100100110 )
b100100110 9
b1 *
b1 @
b11101000 ,
b11101000 B
b11000001 3
b11000001 6
b1100101 2
b1100101 5
b0 4
b0 7
b11110100011000001 1
b11110100011000001 ?
b10100101110100000 -
b10100101110100000 ;
b10001 0
b10001 :
1&
#36
0&
b10010 '
b10010 (
b10010 C
#37
b1001011 ,
b1001011 B
b10100000 +
b10100000 A
b100111 !
b100111 )
b100111 9
b1111100100110110 -
b1111100100110110 ;
b10010 0
b10010 :
b10100101110100000 1
b10100101110100000 ?
b11101000 2
b11101000 5
b1 4
b1 7
1&
#38
0&
b10011 '
b10011 (
b10011 C
#39
b111111111110101011 !
b111111111110101011 )
b111111111110101011 9
b0 *
b0 @
b11111001 ,
b11111001 B
b110110 +
b110110 A
b10100000 3
b10100000 6
b1001011 2
b1001011 5
b1111100100110110 1
b1111100100110110 ?
b1100111011010110 -
b1100111011010110 ;
b10011 0
b10011 :
1&
#40
0&
b10100 '
b10100 (
b10100 C
#41
b11001110 ,
b11001110 B
b11010110 +
b11010110 A
b100101111 !
b100101111 )
b100101111 9
b100110110011010101 -
b100110110011010101 ;
b10100 0
b10100 :
b1100111011010110 1
b1100111011010110 ?
b110110 3
b110110 6
b11111001 2
b11111001 5
b0 4
b0 7
1&
#42
0&
b10101 '
b10101 (
b10101 C
#43
b110100100 !
b110100100 )
b110100100 9
b10 *
b10 @
b1101100 ,
b1101100 B
b11010101 +
b11010101 A
b11010110 3
b11010110 6
b11001110 2
b11001110 5
b100110110011010101 1
b100110110011010101 ?
b110100111111111 -
b110100111111111 ;
b10101 0
b10101 :
1&
#44
0&
b10110 '
b10110 (
b10110 C
#45
b0 *
b0 @
b1101001 ,
b1101001 B
b11111111 +
b11111111 A
b101100111011100 !
b101100111011100 )
b101100111011100 9
b110000000001011111 -
b110000000001011111 ;
b10110 0
b10110 :
b110100111111111 1
b110100111111111 ?
b11010101 3
b11010101 6
b1101100 2
b1101100 5
b10 4
b10 7
1&
#46
0&
b10111 '
b10111 (
b10111 C
#47
b101101000 !
b101101000 )
b101101000 9
b11 *
b11 @
b0 ,
b0 B
b1011111 +
b1011111 A
b11111111 3
b11111111 6
b1101001 2
b1101001 5
b0 4
b0 7
b110000000001011111 1
b110000000001011111 ?
b101100010100010111 -
b101100010100010111 ;
b10111 0
b10111 :
1&
#48
0&
b11000 '
b11000 (
b11000 C
#49
b10 *
b10 @
b11000101 ,
b11000101 B
b10111 +
b10111 A
b0 !
b0 )
b0 9
b101111001000111000 -
b101111001000111000 ;
b11000 0
b11000 :
b101100010100010111 1
b101100010100010111 ?
b1011111 3
b1011111 6
b0 2
b0 5
b11 4
b11 7
1&
#50
0&
b11001 '
b11001 (
b11001 C
#51
b1000110110011 !
b1000110110011 )
b1000110110011 9
b11110010 ,
b11110010 B
b111000 +
b111000 A
b10111 3
b10111 6
b11000101 2
b11000101 5
b10 4
b10 7
b101111001000111000 1
b101111001000111000 ?
b1101110010110010 -
b1101110010110010 ;
b11001 0
b11001 :
1&
#52
0&
b11010 '
b11010 (
b11010 C
#53
b0 *
b0 @
b11011100 ,
b11011100 B
b10110010 +
b10110010 A
b11010011110000 !
b11010011110000 )
b11010011110000 9
b10000110110100010 -
b10000110110100010 ;
b11010 0
b11010 :
b1101110010110010 1
b1101110010110010 ?
b111000 3
b111000 6
b11110010 2
b11110010 5
1&
#54
0&
b11011 '
b11011 (
b11011 C
#55
b110001110 !
b110001110 )
b110001110 9
b1 *
b1 @
b1101 ,
b1101 B
b10100010 +
b10100010 A
b10110010 3
b10110010 6
b11011100 2
b11011100 5
b0 4
b0 7
b10000110110100010 1
b10000110110100010 ?
b100011100101110000 -
b100011100101110000 ;
b11011 0
b11011 :
1&
#56
0&
b11100 '
b11100 (
b11100 C
#57
b10 *
b10 @
b111001 ,
b111001 B
b1110000 +
b1110000 A
b111111111101101011 !
b111111111101101011 )
b111111111101101011 9
b101100011101010110 -
b101100011101010110 ;
b11100 0
b11100 :
b100011100101110000 1
b100011100101110000 ?
b10100010 3
b10100010 6
b1101 2
b1101 5
b1 4
b1 7
1&
#58
0&
b11101 '
b11101 (
b11101 C
#59
b1100011110000 !
b1100011110000 )
b1100011110000 9
b11000111 ,
b11000111 B
b1010110 +
b1010110 A
b1110000 3
b1110000 6
b111001 2
b111001 5
b10 4
b10 7
b101100011101010110 1
b101100011101010110 ?
b11110011011101101 -
b11110011011101101 ;
b11101 0
b11101 :
1&
#60
0&
b11110 '
b11110 (
b11110 C
#61
b1 *
b1 @
b11100110 ,
b11100110 B
b11101101 +
b11101101 A
b100001011011010 !
b100001011011010 )
b100001011011010 9
b1000111111100010 -
b1000111111100010 ;
b11110 0
b11110 :
b11110011011101101 1
b11110011011101101 ?
b1010110 3
b1010110 6
b11000111 2
b11000111 5
1&
#62
0&
b11111 '
b11111 (
b11111 C
#63
b111111111111111001 !
b111111111111111001 )
b111111111111111001 9
b0 *
b0 @
b10001111 ,
b10001111 B
b11100010 +
b11100010 A
b11101101 3
b11101101 6
b11100110 2
b11100110 5
b1 4
b1 7
b1000111111100010 1
b1000111111100010 ?
b111110000001001 -
b111110000001001 ;
b11111 0
b11111 :
1&
#64
0&
b100000 '
b100000 (
b100000 C
#65
b1111100 ,
b1111100 B
b1001 +
b1001 A
b101110001 !
b101110001 )
b101110001 9
b110011101011110000 -
b110011101011110000 ;
b100000 0
b100000 :
b111110000001001 1
b111110000001001 ?
b11100010 3
b11100010 6
b10001111 2
b10001111 5
b0 4
b0 7
1&
#66
0&
b100001 '
b100001 (
b100001 C
#67
b10000101 !
b10000101 )
b10000101 9
b11 *
b11 @
b111010 ,
b111010 B
b11110000 +
b11110000 A
b1001 3
b1001 6
b1111100 2
b1111100 5
b110011101011110000 1
b110011101011110000 ?
b11000001110100110 -
b11000001110100110 ;
b100001 0
b100001 :
1&
#68
0&
b100010 '
b100010 (
b100010 C
#69
b1 *
b1 @
b10000011 ,
b10000011 B
b10100110 +
b10100110 A
b0 !
b0 )
b0 9
b101000000001000101 -
b101000000001000101 ;
b100010 0
b100010 :
b11000001110100110 1
b11000001110100110 ?
b11110000 3
b11110000 6
b111010 2
b111010 5
b11 4
b11 7
1&
#70
0&
b100011 '
b100011 (
b100011 C
#71
b111111111111011101 !
b111111111111011101 )
b111111111111011101 9
b10 *
b10 @
b10000000 ,
b10000000 B
b1000101 +
b1000101 A
b10100110 3
b10100110 6
b10000011 2
b10000011 5
b1 4
b1 7
b101000000001000101 1
b101000000001000101 ?
b100010100110010101 -
b100010100110010101 ;
b100011 0
b100011 :
1&
#72
0&
b100100 '
b100100 (
b100100 C
#73
b101001 ,
b101001 B
b10010101 +
b10010101 A
b10001010000000 !
b10001010000000 )
b10001010000000 9
b111001001001011001 -
b111001001001011001 ;
b100100 0
b100100 :
b100010100110010101 1
b100010100110010101 ?
b1000101 3
b1000101 6
b10000000 2
b10000000 5
b10 4
b10 7
1&
#74
0&
b100101 '
b100101 (
b100101 C
#75
b1011111011101 !
b1011111011101 )
b1011111011101 9
b11 *
b11 @
b10010010 ,
b10010010 B
b1011001 +
b1011001 A
b10010101 3
b10010101 6
b101001 2
b101001 5
b111001001001011001 1
b111001001001011001 ?
b111110001110010111 -
b111110001110010111 ;
b100101 0
b100101 :
1&
#76
0&
b100110 '
b100110 (
b100110 C
#77
b11100011 ,
b11100011 B
b10010111 +
b10010111 A
b1 !
b1 )
b1 9
b101001111010011 -
b101001111010011 ;
b100110 0
b100110 :
b111110001110010111 1
b111110001110010111 ?
b1011001 3
b1011001 6
b10010010 2
b10010010 5
b11 4
b11 7
1&
#78
0&
b100111 '
b100111 (
b100111 C
#79
b0 *
b0 @
b1010011 ,
b1010011 B
b11010011 +
b11010011 A
b10010111 3
b10010111 6
b11100011 2
b11100011 5
b101001111010011 1
b101001111010011 ?
b11001011110010000 -
b11001011110010000 ;
b100111 0
b100111 :
1&
#80
0&
b101000 '
b101000 (
b101000 C
#81
b1 *
b1 @
b10010111 ,
b10010111 B
b10010000 +
b10010000 A
b100100110 !
b100100110 )
b100100110 9
b11100111010111000 -
b11100111010111000 ;
b101000 0
b101000 :
b11001011110010000 1
b11001011110010000 ?
b11010011 3
b11010011 6
b1010011 2
b1010011 5
b0 4
b0 7
1&
#82
0&
b101001 '
b101001 (
b101001 C
#83
b111 !
b111 )
b111 9
b11001110 ,
b11001110 B
b10111000 +
b10111000 A
b10010000 3
b10010000 6
b10010111 2
b10010111 5
b1 4
b1 7
b11100111010111000 1
b11100111010111000 ?
b11100100111000011 -
b11100100111000011 ;
b101001 0
b101001 :
1&
#84
0&
b101010 '
b101010 (
b101010 C
#85
b11001001 ,
b11001001 B
b11000011 +
b11000011 A
b10110 !
b10110 )
b10110 9
b111001000001011100 -
b111001000001011100 ;
b101010 0
b101010 :
b11100100111000011 1
b11100100111000011 ?
b10111000 3
b10111000 6
b11001110 2
b11001110 5
1&
#86
0&
b101011 '
b101011 (
b101011 C
#87
b110 !
b110 )
b110 9
b11 *
b11 @
b10010000 ,
b10010000 B
b1011100 +
b1011100 A
b11000011 3
b11000011 6
b11001001 2
b11001001 5
b111001000001011100 1
b111001000001011100 ?
b100010000010001101 -
b100010000010001101 ;
b101011 0
b101011 :
1&
#88
0&
b101100 '
b101100 (
b101100 C
#89
b10 *
b10 @
b100000 ,
b100000 B
b10001101 +
b10001101 A
b1 !
b1 )
b1 9
b101101111000111000 -
b101101111000111000 ;
b101100 0
b101100 :
b100010000010001101 1
b100010000010001101 ?
b1011100 3
b1011100 6
b10010000 2
b10010000 5
b11 4
b11 7
1&
#90
0&
b101101 '
b101101 (
b101101 C
#91
b1000110100000 !
b1000110100000 )
b1000110100000 9
b11011110 ,
b11011110 B
b111000 +
b111000 A
b10001101 3
b10001101 6
b100000 2
b100000 5
b10 4
b10 7
b101101111000111000 1
b101101111000111000 ?
b110101111100000010 -
b110101111100000010 ;
b101101 0
b101101 :
1&
#92
0&
b101110 '
b101110 (
b101110 C
#93
b11 *
b11 @
b1011111 ,
b1011111 B
b10 +
b10 A
b11000010010000 !
b11000010010000 )
b11000010010000 9
b101011101111101111 -
b101011101111101111 ;
b101110 0
b101110 :
b110101111100000010 1
b110101111100000010 ?
b111000 3
b111000 6
b11011110 2
b11011110 5
1&
#94
0&
b101111 '
b101111 (
b101111 C
#95
b101111 !
b101111 )
b101111 9
b10 *
b10 @
b10111011 ,
b10111011 B
b11101111 +
b11101111 A
b10 3
b10 6
b1011111 2
b1011111 5
b11 4
b11 7
b101011101111101111 1
b101011101111101111 ?
b10001111101000101 -
b10001111101000101 ;
b101111 0
b101111 :
1&
#96
0&
b110000 '
b110000 (
b110000 C
#97
b1 *
b1 @
b11111 ,
b11111 B
b1000101 +
b1000101 A
b1010111010010101 !
b1010111010010101 )
b1010111010010101 9
b100100101011000 -
b100100101011000 ;
b110000 0
b110000 :
b10001111101000101 1
b10001111101000101 ?
b11101111 3
b11101111 6
b10111011 2
b10111011 5
b10 4
b10 7
1&
#98
0&
b110001 '
b110001 (
b110001 C
#99
b111111111111011010 !
b111111111111011010 )
b111111111111011010 9
b0 *
b0 @
b1001001 ,
b1001001 B
b1011000 +
b1011000 A
b1000101 3
b1000101 6
b11111 2
b11111 5
b1 4
b1 7
b100100101011000 1
b100100101011000 ?
b101111111000001100 -
b101111111000001100 ;
b110001 0
b110001 :
1&
#100
0&
b110010 '
b110010 (
b110010 C
#101
b10 *
b10 @
b11111110 ,
b11111110 B
b1100 +
b1100 A
b10100001 !
b10100001 )
b10100001 9
b101111010111101000 -
b101111010111101000 ;
b110010 0
b110010 :
b101111111000001100 1
b101111111000001100 ?
b1011000 3
b1011000 6
b1001001 2
b1001001 5
b0 4
b0 7
1&
#102
0&
b110011 '
b110011 (
b110011 C
#103
b101111101000 !
b101111101000 )
b101111101000 9
b11110101 ,
b11110101 B
b11101000 +
b11101000 A
b1100 3
b1100 6
b11111110 2
b11111110 5
b10 4
b10 7
b101111010111101000 1
b101111010111101000 ?
b11100011110010110 -
b11100011110010110 ;
b110011 0
b110011 :
1&
#104
0&
b110100 '
b110100 (
b110100 C
#105
b1 *
b1 @
b11000111 ,
b11000111 B
b10010110 +
b10010110 A
b1101111000001000 !
b1101111000001000 )
b1101111000001000 9
b100101010000110001 -
b100101010000110001 ;
b110100 0
b110100 :
b11100011110010110 1
b11100011110010110 ?
b11101000 3
b11101000 6
b11110101 2
b11110101 5
1&
#106
0&
b110101 '
b110101 (
b110101 C
#107
b110001 !
b110001 )
b110001 9
b10 *
b10 @
b1010100 ,
b1010100 B
b110001 +
b110001 A
b10010110 3
b10010110 6
b11000111 2
b11000111 5
b1 4
b1 7
b100101010000110001 1
b100101010000110001 ?
b111001001101110 -
b111001001101110 ;
b110101 0
b110101 :
1&
#108
0&
b110110 '
b110110 (
b110110 C
#109
b0 *
b0 @
b1110010 ,
b1110010 B
b1101110 +
b1101110 A
b1000000010100 !
b1000000010100 )
b1000000010100 9
b1000101010001110 -
b1000101010001110 ;
b110110 0
b110110 :
b111001001101110 1
b111001001101110 ?
b110001 3
b110001 6
b1010100 2
b1010100 5
b10 4
b10 7
1&
#110
0&
b110111 '
b110111 (
b110111 C
#111
b11100000 !
b11100000 )
b11100000 9
b10001010 ,
b10001010 B
b10001110 +
b10001110 A
b1101110 3
b1101110 6
b1110010 2
b1110010 5
b0 4
b0 7
b1000101010001110 1
b1000101010001110 ?
b1100101000110010 -
b1100101000110010 ;
b110111 0
b110111 :
1&
#112
0&
b111000 '
b111000 (
b111000 C
#113
b11001010 ,
b11001010 B
b110010 +
b110010 A
b100011000 !
b100011000 )
b100011000 9
b1100000011010100 -
b1100000011010100 ;
b111000 0
b111000 :
b1100101000110010 1
b1100101000110010 ?
b10001110 3
b10001110 6
b10001010 2
b10001010 5
1&
#114
0&
b111001 '
b111001 (
b111001 C
#115
b11111100 !
b11111100 )
b11111100 9
b11000000 ,
b11000000 B
b11010100 +
b11010100 A
b110010 3
b110010 6
b11001010 2
b11001010 5
b1100000011010100 1
b1100000011010100 ?
b101101111111101011 -
b101101111111101011 ;
b111001 0
b111001 :
1&
#116
0&
b111010 '
b111010 (
b111010 C
#117
b10 *
b10 @
b11011111 ,
b11011111 B
b11101011 +
b11101011 A
b110010100 !
b110010100 )
b110010100 9
b111000010001100011 -
b111000010001100011 ;
b111010 0
b111010 :
b101101111111101011 1
b101101111111101011 ?
b11010100 3
b11010100 6
b11000000 2
b11000000 5
1&
