UART_TX/UART_TX.v
// UART Transmitter :  
// This transmitter is able to transmit 8 bits of serial data, one start bit, one stop bit,
// and no parity bit.  When transmit is complete o_Tx_done will be driven high for one clock cycle.
//
// Set Parameter CLKS_PER_BIT as follows:
// CLKS_PER_BIT = (Frequency of i_Clock)/(Frequency of UART)
// Example: 25 MHz Clock, 115200 baud UART
// (25000000)/(115200) = 217
 
module UART_TX 
  #(parameter CLKS_PER_BIT = 217)
  (
   input       i_Rst_L,
   input       i_Clock,
   input       i_TX_DV,
   input [7:0] i_TX_Byte, 
   output reg  o_TX_Active,
   output reg  o_TX_Serial,
   output reg  o_TX_Done
   );
 
  localparam IDLE         = 2'b00;
  localparam TX_START_BIT = 2'b01;
  localparam TX_DATA_BITS = 2'b10;
  localparam TX_STOP_BIT  = 2'b11;
  
  reg [2:0] r_SM_Main;
  reg [$clog2(CLKS_PER_BIT):0] r_Clock_Count;
  reg [2:0] r_Bit_Index;
  reg [7:0] r_TX_Data;


  // Purpose: Control TX state machine
  always @(posedge i_Clock or negedge i_Rst_L)
  begin
    if (~i_Rst_L)
    begin
      r_SM_Main <= 3'b000;
    end
    else
    begin

      o_TX_Done <= 1'b0;

      case (r_SM_Main)
      IDLE :
        begin
          o_TX_Serial   <= 1'b1;         // Drive Line High for Idle
          r_Clock_Count <= 0;
          r_Bit_Index   <= 0;
          
          if (i_TX_DV == 1'b1)
          begin
            o_TX_Active <= 1'b1;
            r_TX_Data   <= i_TX_Byte;
            r_SM_Main   <= TX_START_BIT;
          end
          else
            r_SM_Main <= IDLE;
        end // case: IDLE
      
      
      // Send out Start Bit. Start bit = 0
      TX_START_BIT :
        begin
          o_TX_Serial <= 1'b0;
          
          // Wait CLKS_PER_BIT-1 clock cycles for start bit to finish
          if (r_Clock_Count < CLKS_PER_BIT-1)
          begin
            r_Clock_Count <= r_Clock_Count + 1;
            r_SM_Main     <= TX_START_BIT;
          end
          else
          begin
            r_Clock_Count <= 0;
            r_SM_Main     <= TX_DATA_BITS;
          end
        end // case: TX_START_BIT
      
      
      // Wait CLKS_PER_BIT-1 clock cycles for data bits to finish         
      TX_DATA_BITS :
        begin
          o_TX_Serial <= r_TX_Data[r_Bit_Index];
          
          if (r_Clock_Count < CLKS_PER_BIT-1)
          begin
            r_Clock_Count <= r_Clock_Count + 1;
            r_SM_Main     <= TX_DATA_BITS;
          end
          else
          begin
            r_Clock_Count <= 0;
            
            // Check if we have sent out all bits
            if (r_Bit_Index < 7)
            begin
              r_Bit_Index <= r_Bit_Index + 1;
              r_SM_Main   <= TX_DATA_BITS;
            end
            else
            begin
              r_Bit_Index <= 0;
              r_SM_Main   <= TX_STOP_BIT;
            end
          end 
        end // case: TX_DATA_BITS
      
      
      // Send out Stop bit.  Stop bit = 1
      TX_STOP_BIT :
        begin
          o_TX_Serial <= 1'b1;
          
          // Wait CLKS_PER_BIT-1 clock cycles for Stop bit to finish
          if (r_Clock_Count < CLKS_PER_BIT-1)
          begin
            r_Clock_Count <= r_Clock_Count + 1;
            r_SM_Main     <= TX_STOP_BIT;
          end
          else
          begin
            o_TX_Done     <= 1'b1;
            r_Clock_Count <= 0;
            r_SM_Main     <= IDLE;
            o_TX_Active   <= 1'b0;
          end 
        end // case: TX_STOP_BIT      
      
      default :
        r_SM_Main <= IDLE;
      
    endcase
    end // else: !if(~i_Rst_L)
  end // always @ (posedge i_Clock or negedge i_Rst_L)

  
endmodule

module UART_RX
  #(parameter CLKS_PER_BIT = 217)
  (
   input        i_Clock,
   input        i_RX_Serial,
   output       o_RX_DV,
   output [7:0] o_RX_Byte
   );
   
  parameter IDLE         = 3'b000;
  parameter RX_START_BIT = 3'b001;
  parameter RX_DATA_BITS = 3'b010;
  parameter RX_STOP_BIT  = 3'b011;
  parameter CLEANUP      = 3'b100;
  
  reg [7:0] r_Clock_Count = 0;
  reg [2:0] r_Bit_Index   = 0; //8 bits total
  reg [7:0] r_RX_Byte     = 0;
  reg       r_RX_DV       = 0;
  reg [2:0] r_SM_Main     = 0;
  
  
  // Purpose: Control RX state machine
  always @(posedge i_Clock)
  begin
      
    case (r_SM_Main)
      IDLE :
        begin
          r_RX_DV       <= 1'b0;
          r_Clock_Count <= 0;
          r_Bit_Index   <= 0;
          
          if (i_RX_Serial == 1'b0)          // Start bit detected
            r_SM_Main <= RX_START_BIT;
          else
            r_SM_Main <= IDLE;
        end
      
      // Check middle of start bit to make sure it's still low
      RX_START_BIT :
        begin
          if (r_Clock_Count == (CLKS_PER_BIT-1)/2)
          begin
            if (i_RX_Serial == 1'b0)
            begin
              r_Clock_Count <= 0;  // reset counter, found the middle
              r_SM_Main     <= RX_DATA_BITS;
            end
            else
              r_SM_Main <= IDLE;
          end
          else
          begin
            r_Clock_Count <= r_Clock_Count + 1;
            r_SM_Main     <= RX_START_BIT;
          end
        end // case: RX_START_BIT
      
      
      // Wait CLKS_PER_BIT-1 clock cycles to sample serial data
      RX_DATA_BITS :
        begin
          if (r_Clock_Count < CLKS_PER_BIT-1)
          begin
            r_Clock_Count <= r_Clock_Count + 1;
            r_SM_Main     <= RX_DATA_BITS;
          end
          else
          begin
            r_Clock_Count          <= 0;
            r_RX_Byte[r_Bit_Index] <= i_RX_Serial;
            
            // Check if we have received all bits
            if (r_Bit_Index < 7)
            begin
              r_Bit_Index <= r_Bit_Index + 1;
              r_SM_Main   <= RX_DATA_BITS;
            end
            else
            begin
              r_Bit_Index <= 0;
              r_SM_Main   <= RX_STOP_BIT;
            end
          end
        end // case: RX_DATA_BITS
      
      
      // Receive Stop bit.  Stop bit = 1
      RX_STOP_BIT :
        begin
          // Wait CLKS_PER_BIT-1 clock cycles for Stop bit to finish
          if (r_Clock_Count < CLKS_PER_BIT-1)
          begin
            r_Clock_Count <= r_Clock_Count + 1;
     	    r_SM_Main     <= RX_STOP_BIT;
          end
          else
          begin
       	    r_RX_DV       <= 1'b1;
            r_Clock_Count <= 0;
            r_SM_Main     <= CLEANUP;
          end
        end // case: RX_STOP_BIT
      
      
      // Stay here 1 clock
      CLEANUP :
        begin
          r_SM_Main <= IDLE;
          r_RX_DV   <= 1'b0;
        end
      
      
      default :
        r_SM_Main <= IDLE;
      
    endcase
  end    
  
  assign o_RX_DV   = r_RX_DV;
  assign o_RX_Byte = r_RX_Byte;
  
endmodule // UART_RX

UART_TX/UART_tb.v
// This file id downloaded from http://www.nandland.com

// This testbench will exercise the UART RX.
// It sends out byte 0x37, and ensures the RX receives it correctly.
`timescale 1ns/10ps

`include "UART_TX.v"

module UART_TB ();

  // Testbench uses a 25 MHz clock
  // Want to interface to 115200 baud UART
  // 25000000 / 115200 = 217 Clocks Per Bit.
  parameter c_CLOCK_PERIOD_NS = 40;
  parameter c_CLKS_PER_BIT    = 217;
  parameter c_BIT_PERIOD      = 8600;
  
  reg r_Clock = 0;
  reg r_TX_DV = 0;
  wire w_TX_Active, w_UART_Line;
  wire w_TX_Serial;
  reg [7:0] r_TX_Byte = 0;
  wire [7:0] w_RX_Byte;

  UART_RX #(.CLKS_PER_BIT(c_CLKS_PER_BIT)) UART_RX_Inst
    (.i_Clock(r_Clock),
     .i_RX_Serial(w_UART_Line),
     .o_RX_DV(w_RX_DV),
     .o_RX_Byte(w_RX_Byte)
     );
  
  UART_TX #(.CLKS_PER_BIT(c_CLKS_PER_BIT)) UART_TX_Inst
    (.i_Clock(r_Clock),
     .i_TX_DV(r_TX_DV),
     .i_TX_Byte(r_TX_Byte),
     .o_TX_Active(w_TX_Active),
     .o_TX_Serial(w_TX_Serial),
     .o_TX_Done()
     );

  // Keeps the UART Receive input high (default) when
  // UART transmitter is not active
  assign w_UART_Line = w_TX_Active ? w_TX_Serial : 1'b1;
    
  always
    #(c_CLOCK_PERIOD_NS/2) r_Clock <= !r_Clock;
  
  // Main Testing:
  initial
    begin
      $dumpfile("UART_tb.vcd");
      $dumpvars(0,UART_tb);
      // Tell UART to send a command (exercise TX)
      @(posedge r_Clock);
      @(posedge r_Clock);
      r_TX_DV   <= 1'b1;
      r_TX_Byte <= 8'h3F;
      @(posedge r_Clock);
      r_TX_DV <= 1'b0;

      // Check that the correct command was received
      @(posedge w_RX_DV);
      if (w_RX_Byte == 8'h3F)
        $display("Test Passed - Correct Byte Received");
      else
        $display("Test Failed - Incorrect Byte Received");
      $finish();
    end
  
  initial 
  begin
    // Required to dump signals to EPWave
    $dumpfile("dump.vcd");
    $dumpvars(0);
  end
endmodule

UART_TX/dump.vcd
$date
	Wed Feb 15 11:50:08 2023
$end
$version
	Icarus Verilog
$end
$timescale
	10ps
$end
$scope module UART_TB $end
$var wire 1 ! w_UART_Line $end
$var wire 1 " w_TX_Serial $end
$var wire 1 # w_TX_Active $end
$var wire 1 $ w_RX_DV $end
$var wire 8 % w_RX_Byte [7:0] $end
$var parameter 32 & c_BIT_PERIOD $end
$var parameter 32 ' c_CLKS_PER_BIT $end
$var parameter 32 ( c_CLOCK_PERIOD_NS $end
$var reg 1 ) r_Clock $end
$var reg 8 * r_TX_Byte [7:0] $end
$var reg 1 + r_TX_DV $end
$scope module UART_RX_Inst $end
$var wire 1 ) i_Clock $end
$var wire 1 ! i_RX_Serial $end
$var wire 8 , o_RX_Byte [7:0] $end
$var wire 1 $ o_RX_DV $end
$var parameter 3 - CLEANUP $end
$var parameter 32 . CLKS_PER_BIT $end
$var parameter 3 / IDLE $end
$var parameter 3 0 RX_DATA_BITS $end
$var parameter 3 1 RX_START_BIT $end
$var parameter 3 2 RX_STOP_BIT $end
$var reg 3 3 r_Bit_Index [2:0] $end
$var reg 8 4 r_Clock_Count [7:0] $end
$var reg 8 5 r_RX_Byte [7:0] $end
$var reg 1 6 r_RX_DV $end
$var reg 3 7 r_SM_Main [2:0] $end
$upscope $end
$scope module UART_TX_Inst $end
$var wire 1 ) i_Clock $end
$var wire 1 8 i_Rst_L $end
$var wire 8 9 i_TX_Byte [7:0] $end
$var wire 1 + i_TX_DV $end
$var parameter 32 : CLKS_PER_BIT $end
$var parameter 2 ; IDLE $end
$var parameter 2 < TX_DATA_BITS $end
$var parameter 2 = TX_START_BIT $end
$var parameter 2 > TX_STOP_BIT $end
$var reg 1 # o_TX_Active $end
$var reg 1 ? o_TX_Done $end
$var reg 1 " o_TX_Serial $end
$var reg 3 @ r_Bit_Index [2:0] $end
$var reg 9 A r_Clock_Count [8:0] $end
$var reg 3 B r_SM_Main [2:0] $end
$var reg 8 C r_TX_Data [7:0] $end
$upscope $end
$upscope $end
$enddefinitions $end
$comment Show the parameter values. $end
$dumpall
b11 >
b1 =
b10 <
b0 ;
b11011001 :
b11 2
b1 1
b10 0
b0 /
b11011001 .
b100 -
b101000 (
b11011001 '
b10000110011000 &
$end
#0
$dumpvars
bx C
bx B
bx A
bx @
x?
b0 9
z8
b0 7
06
b0 5
b0 4
b0 3
b0 ,
0+
b0 *
0)
b0 %
0$
x#
x"
x!
$end
#2000
b0 B
0?
1)
#4000
0)
#6000
1!
b111111 *
b111111 9
1+
b0 @
b0 A
1"
1)
#8000
0)
#10000
0+
b1 B
b111111 C
1#
1)
#12000
0)
#14000
0!
b1 A
0"
1)
#16000
0)
#18000
b1 7
b10 A
1)
#20000
0)
#22000
b1 4
b11 A
1)
#24000
0)
#26000
b10 4
b100 A
1)
#28000
0)
#30000
b11 4
b101 A
1)
#32000
0)
#34000
b100 4
b110 A
1)
#36000
0)
#38000
b101 4
b111 A
1)
#40000
0)
#42000
b110 4
b1000 A
1)
#44000
0)
#46000
b111 4
b1001 A
1)
#48000
0)
#50000
b1000 4
b1010 A
1)
#52000
0)
#54000
b1001 4
b1011 A
1)
#56000
0)
#58000
b1010 4
b1100 A
1)
#60000
0)
#62000
b1011 4
b1101 A
1)
#64000
0)
#66000
b1100 4
b1110 A
1)
#68000
0)
#70000
b1101 4
b1111 A
1)
#72000
0)
#74000
b1110 4
b10000 A
1)
#76000
0)
#78000
b1111 4
b10001 A
1)
#80000
0)
#82000
b10000 4
b10010 A
1)
#84000
0)
#86000
b10001 4
b10011 A
1)
#88000
0)
#90000
b10010 4
b10100 A
1)
#92000
0)
#94000
b10011 4
b10101 A
1)
#96000
0)
#98000
b10100 4
b10110 A
1)
#100000
0)
#102000
b10101 4
b10111 A
1)
#104000
0)
#106000
b10110 4
b11000 A
1)
#108000
0)
#110000
b10111 4
b11001 A
1)
#112000
0)
#114000
b11000 4
b11010 A
1)
#116000
0)
#118000
b11001 4
b11011 A
1)
#120000
0)
#122000
b11010 4
b11100 A
1)
#124000
0)
#126000
b11011 4
b11101 A
1)
#128000
0)
#130000
b11100 4
b11110 A
1)
#132000
0)
#134000
b11101 4
b11111 A
1)
#136000
0)
#138000
b11110 4
b100000 A
1)
#140000
0)
#142000
b11111 4
b100001 A
1)
#144000
0)
#146000
b100000 4
b100010 A
1)
#148000
0)
#150000
b100001 4
b100011 A
1)
#152000
0)
#154000
b100010 4
b100100 A
1)
#156000
0)
#158000
b100011 4
b100101 A
1)
#160000
0)
#162000
b100100 4
b100110 A
1)
#164000
0)
#166000
b100101 4
b100111 A
1)
#168000
0)
#170000
b100110 4
b101000 A
1)
#172000
0)
#174000
b100111 4
b101001 A
1)
#176000
0)
#178000
b101000 4
b101010 A
1)
#180000
0)
#182000
b101001 4
b101011 A
1)
#184000
0)
#186000
b101010 4
b101100 A
1)
#188000
0)
#190000
b101011 4
b101101 A
1)
#192000
0)
#194000
b101100 4
b101110 A
1)
#196000
0)
#198000
b101101 4
b101111 A
1)
#200000
0)
#202000
b101110 4
b110000 A
1)
#204000
0)
#206000
b101111 4
b110001 A
1)
#208000
0)
#210000
b110000 4
b110010 A
1)
#212000
0)
#214000
b110001 4
b110011 A
1)
#216000
0)
#218000
b110010 4
b110100 A
1)
#220000
0)
#222000
b110011 4
b110101 A
1)
#224000
0)
#226000
b110100 4
b110110 A
1)
#228000
0)
#230000
b110101 4
b110111 A
1)
#232000
0)
#234000
b110110 4
b111000 A
1)
#236000
0)
#238000
b110111 4
b111001 A
1)
#240000
0)
#242000
b111000 4
b111010 A
1)
#244000
0)
#246000
b111001 4
b111011 A
1)
#248000
0)
#250000
b111010 4
b111100 A
1)
#252000
0)
#254000
b111011 4
b111101 A
1)
#256000
0)
#258000
b111100 4
b111110 A
1)
#260000
0)
#262000
b111101 4
b111111 A
1)
#264000
0)
#266000
b111110 4
b1000000 A
1)
#268000
0)
#270000
b111111 4
b1000001 A
1)
#272000
0)
#274000
b1000000 4
b1000010 A
1)
#276000
0)
#278000
b1000001 4
b1000011 A
1)
#280000
0)
#282000
b1000010 4
b1000100 A
1)
#284000
0)
#286000
b1000011 4
b1000101 A
1)
#288000
0)
#290000
b1000100 4
b1000110 A
1)
#292000
0)
#294000
b1000101 4
b1000111 A
1)
#296000
0)
#298000
b1000110 4
b1001000 A
1)
#300000
0)
#302000
b1000111 4
b1001001 A
1)
#304000
0)
#306000
b1001000 4
b1001010 A
1)
#308000
0)
#310000
b1001001 4
b1001011 A
1)
#312000
0)
#314000
b1001010 4
b1001100 A
1)
#316000
0)
#318000
b1001011 4
b1001101 A
1)
#320000
0)
#322000
b1001100 4
b1001110 A
1)
#324000
0)
#326000
b1001101 4
b1001111 A
1)
#328000
0)
#330000
b1001110 4
b1010000 A
1)
#332000
0)
#334000
b1001111 4
b1010001 A
1)
#336000
0)
#338000
b1010000 4
b1010010 A
1)
#340000
0)
#342000
b1010001 4
b1010011 A
1)
#344000
0)
#346000
b1010010 4
b1010100 A
1)
#348000
0)
#350000
b1010011 4
b1010101 A
1)
#352000
0)
#354000
b1010100 4
b1010110 A
1)
#356000
0)
#358000
b1010101 4
b1010111 A
1)
#360000
0)
#362000
b1010110 4
b1011000 A
1)
#364000
0)
#366000
b1010111 4
b1011001 A
1)
#368000
0)
#370000
b1011000 4
b1011010 A
1)
#372000
0)
#374000
b1011001 4
b1011011 A
1)
#376000
0)
#378000
b1011010 4
b1011100 A
1)
#380000
0)
#382000
b1011011 4
b1011101 A
1)
#384000
0)
#386000
b1011100 4
b1011110 A
1)
#388000
0)
#390000
b1011101 4
b1011111 A
1)
#392000
0)
#394000
b1011110 4
b1100000 A
1)
#396000
0)
#398000
b1011111 4
b1100001 A
1)
#400000
0)
#402000
b1100000 4
b1100010 A
1)
#404000
0)
#406000
b1100001 4
b1100011 A
1)
#408000
0)
#410000
b1100010 4
b1100100 A
1)
#412000
0)
#414000
b1100011 4
b1100101 A
1)
#416000
0)
#418000
b1100100 4
b1100110 A
1)
#420000
0)
#422000
b1100101 4
b1100111 A
1)
#424000
0)
#426000
b1100110 4
b1101000 A
1)
#428000
0)
#430000
b1100111 4
b1101001 A
1)
#432000
0)
#434000
b1101000 4
b1101010 A
1)
#436000
0)
#438000
b1101001 4
b1101011 A
1)
#440000
0)
#442000
b1101010 4
b1101100 A
1)
#444000
0)
#446000
b1101011 4
b1101101 A
1)
#448000
0)
#450000
b1101100 4
b1101110 A
1)
#452000
0)
#454000
b10 7
b0 4
b1101111 A
1)
#456000
0)
#458000
b1 4
b1110000 A
1)
#460000
0)
#462000
b10 4
b1110001 A
1)
#464000
0)
#466000
b11 4
b1110010 A
1)
#468000
0)
#470000
b100 4
b1110011 A
1)
#472000
0)
#474000
b101 4
b1110100 A
1)
#476000
0)
#478000
b110 4
b1110101 A
1)
#480000
0)
#482000
b111 4
b1110110 A
1)
#484000
0)
#486000
b1000 4
b1110111 A
1)
#488000
0)
#490000
b1001 4
b1111000 A
1)
#492000
0)
#494000
b1010 4
b1111001 A
1)
#496000
0)
#498000
b1011 4
b1111010 A
1)
#500000
0)
#502000
b1100 4
b1111011 A
1)
#504000
0)
#506000
b1101 4
b1111100 A
1)
#508000
0)
#510000
b1110 4
b1111101 A
1)
#512000
0)
#514000
b1111 4
b1111110 A
1)
#516000
0)
#518000
b10000 4
b1111111 A
1)
#520000
0)
#522000
b10001 4
b10000000 A
1)
#524000
0)
#526000
b10010 4
b10000001 A
1)
#528000
0)
#530000
b10011 4
b10000010 A
1)
#532000
0)
#534000
b10100 4
b10000011 A
1)
#536000
0)
#538000
b10101 4
b10000100 A
1)
#540000
0)
#542000
b10110 4
b10000101 A
1)
#544000
0)
#546000
b10111 4
b10000110 A
1)
#548000
0)
#550000
b11000 4
b10000111 A
1)
#552000
0)
#554000
b11001 4
b10001000 A
1)
#556000
0)
#558000
b11010 4
b10001001 A
1)
#560000
0)
#562000
b11011 4
b10001010 A
1)
#564000
0)
#566000
b11100 4
b10001011 A
1)
#568000
0)
#570000
b11101 4
b10001100 A
1)
#572000
0)
#574000
b11110 4
b10001101 A
1)
#576000
0)
#578000
b11111 4
b10001110 A
1)
#580000
0)
#582000
b100000 4
b10001111 A
1)
#584000
0)
#586000
b100001 4
b10010000 A
1)
#588000
0)
#590000
b100010 4
b10010001 A
1)
#592000
0)
#594000
b100011 4
b10010010 A
1)
#596000
0)
#598000
b100100 4
b10010011 A
1)
#600000
0)
#602000
b100101 4
b10010100 A
1)
#604000
0)
#606000
b100110 4
b10010101 A
1)
#608000
0)
#610000
b100111 4
b10010110 A
1)
#612000
0)
#614000
b101000 4
b10010111 A
1)
#616000
0)
#618000
b101001 4
b10011000 A
1)
#620000
0)
#622000
b101010 4
b10011001 A
1)
#624000
0)
#626000
b101011 4
b10011010 A
1)
#628000
0)
#630000
b101100 4
b10011011 A
1)
#632000
0)
#634000
b101101 4
b10011100 A
1)
#636000
0)
#638000
b101110 4
b10011101 A
1)
#640000
0)
#642000
b101111 4
b10011110 A
1)
#644000
0)
#646000
b110000 4
b10011111 A
1)
#648000
0)
#650000
b110001 4
b10100000 A
1)
#652000
0)
#654000
b110010 4
b10100001 A
1)
#656000
0)
#658000
b110011 4
b10100010 A
1)
#660000
0)
#662000
b110100 4
b10100011 A
1)
#664000
0)
#666000
b110101 4
b10100100 A
1)
#668000
0)
#670000
b110110 4
b10100101 A
1)
#672000
0)
#674000
b110111 4
b10100110 A
1)
#676000
0)
#678000
b111000 4
b10100111 A
1)
#680000
0)
#682000
b111001 4
b10101000 A
1)
#684000
0)
#686000
b111010 4
b10101001 A
1)
#688000
0)
#690000
b111011 4
b10101010 A
1)
#692000
0)
#694000
b111100 4
b10101011 A
1)
#696000
0)
#698000
b111101 4
b10101100 A
1)
#700000
0)
#702000
b111110 4
b10101101 A
1)
#704000
0)
#706000
b111111 4
b10101110 A
1)
#708000
0)
#710000
b1000000 4
b10101111 A
1)
#712000
0)
#714000
b1000001 4
b10110000 A
1)
#716000
0)
#718000
b1000010 4
b10110001 A
1)
#720000
0)
#722000
b1000011 4
b10110010 A
1)
#724000
0)
#726000
b1000100 4
b10110011 A
1)
#728000
0)
#730000
b1000101 4
b10110100 A
1)
#732000
0)
#734000
b1000110 4
b10110101 A
1)
#736000
0)
#738000
b1000111 4
b10110110 A
1)
#740000
0)
#742000
b1001000 4
b10110111 A
1)
#744000
0)
#746000
b1001001 4
b10111000 A
1)
#748000
0)
#750000
b1001010 4
b10111001 A
1)
#752000
0)
#754000
b1001011 4
b10111010 A
1)
#756000
0)
#758000
b1001100 4
b10111011 A
1)
#760000
0)
#762000
b1001101 4
b10111100 A
1)
#764000
0)
#766000
b1001110 4
b10111101 A
1)
#768000
0)
#770000
b1001111 4
b10111110 A
1)
#772000
0)
#774000
b1010000 4
b10111111 A
1)
#776000
0)
#778000
b1010001 4
b11000000 A
1)
#780000
0)
#782000
b1010010 4
b11000001 A
1)
#784000
0)
#786000
b1010011 4
b11000010 A
1)
#788000
0)
#790000
b1010100 4
b11000011 A
1)
#792000
0)
#794000
b1010101 4
b11000100 A
1)
#796000
0)
#798000
b1010110 4
b11000101 A
1)
#800000
0)
#802000
b1010111 4
b11000110 A
1)
#804000
0)
#806000
b1011000 4
b11000111 A
1)
#808000
0)
#810000
b1011001 4
b11001000 A
1)
#812000
0)
#814000
b1011010 4
b11001001 A
1)
#816000
0)
#818000
b1011011 4
b11001010 A
1)
#820000
0)
#822000
b1011100 4
b11001011 A
1)
#824000
0)
#826000
b1011101 4
b11001100 A
1)
#828000
0)
#830000
b1011110 4
b11001101 A
1)
#832000
0)
#834000
b1011111 4
b11001110 A
1)
#836000
0)
#838000
b1100000 4
b11001111 A
1)
#840000
0)
#842000
b1100001 4
b11010000 A
1)
#844000
0)
#846000
b1100010 4
b11010001 A
1)
#848000
0)
#850000
b1100011 4
b11010010 A
1)
#852000
0)
#854000
b1100100 4
b11010011 A
1)
#856000
0)
#858000
b1100101 4
b11010100 A
1)
#860000
0)
#862000
b1100110 4
b11010101 A
1)
#864000
0)
#866000
b1100111 4
b11010110 A
1)
#868000
0)
#870000
b1101000 4
b11010111 A
1)
#872000
0)
#874000
b1101001 4
b11011000 A
1)
#876000
0)
#878000
b1101010 4
b10 B
b0 A
1)
#880000
0)
#882000
1!
b1101011 4
b1 A
1"
1)
#884000
0)
#886000
b1101100 4
b10 A
1)
#888000
0)
#890000
b1101101 4
b11 A
1)
#892000
0)
#894000
b1101110 4
b100 A
1)
#896000
0)
#898000
b1101111 4
b101 A
1)
#900000
0)
#902000
b1110000 4
b110 A
1)
#904000
0)
#906000
b1110001 4
b111 A
1)
#908000
0)
#910000
b1110010 4
b1000 A
1)
#912000
0)
#914000
b1110011 4
b1001 A
1)
#916000
0)
#918000
b1110100 4
b1010 A
1)
#920000
0)
#922000
b1110101 4
b1011 A
1)
#924000
0)
#926000
b1110110 4
b1100 A
1)
#928000
0)
#930000
b1110111 4
b1101 A
1)
#932000
0)
#934000
b1111000 4
b1110 A
1)
#936000
0)
#938000
b1111001 4
b1111 A
1)
#940000
0)
#942000
b1111010 4
b10000 A
1)
#944000
0)
#946000
b1111011 4
b10001 A
1)
#948000
0)
#950000
b1111100 4
b10010 A
1)
#952000
0)
#954000
b1111101 4
b10011 A
1)
#956000
0)
#958000
b1111110 4
b10100 A
1)
#960000
0)
#962000
b1111111 4
b10101 A
1)
#964000
0)
#966000
b10000000 4
b10110 A
1)
#968000
0)
#970000
b10000001 4
b10111 A
1)
#972000
0)
#974000
b10000010 4
b11000 A
1)
#976000
0)
#978000
b10000011 4
b11001 A
1)
#980000
0)
#982000
b10000100 4
b11010 A
1)
#984000
0)
#986000
b10000101 4
b11011 A
1)
#988000
0)
#990000
b10000110 4
b11100 A
1)
#992000
0)
#994000
b10000111 4
b11101 A
1)
#996000
0)
#998000
b10001000 4
b11110 A
1)
#1000000
0)
#1002000
b10001001 4
b11111 A
1)
#1004000
0)
#1006000
b10001010 4
b100000 A
1)
#1008000
0)
#1010000
b10001011 4
b100001 A
1)
#1012000
0)
#1014000
b10001100 4
b100010 A
1)
#1016000
0)
#1018000
b10001101 4
b100011 A
1)
#1020000
0)
#1022000
b10001110 4
b100100 A
1)
#1024000
0)
#1026000
b10001111 4
b100101 A
1)
#1028000
0)
#1030000
b10010000 4
b100110 A
1)
#1032000
0)
#1034000
b10010001 4
b100111 A
1)
#1036000
0)
#1038000
b10010010 4
b101000 A
1)
#1040000
0)
#1042000
b10010011 4
b101001 A
1)
#1044000
0)
#1046000
b10010100 4
b101010 A
1)
#1048000
0)
#1050000
b10010101 4
b101011 A
1)
#1052000
0)
#1054000
b10010110 4
b101100 A
1)
#1056000
0)
#1058000
b10010111 4
b101101 A
1)
#1060000
0)
#1062000
b10011000 4
b101110 A
1)
#1064000
0)
#1066000
b10011001 4
b101111 A
1)
#1068000
0)
#1070000
b10011010 4
b110000 A
1)
#1072000
0)
#1074000
b10011011 4
b110001 A
1)
#1076000
0)
#1078000
b10011100 4
b110010 A
1)
#1080000
0)
#1082000
b10011101 4
b110011 A
1)
#1084000
0)
#1086000
b10011110 4
b110100 A
1)
#1088000
0)
#1090000
b10011111 4
b110101 A
1)
#1092000
0)
#1094000
b10100000 4
b110110 A
1)
#1096000
0)
#1098000
b10100001 4
b110111 A
1)
#1100000
0)
#1102000
b10100010 4
b111000 A
1)
#1104000
0)
#1106000
b10100011 4
b111001 A
1)
#1108000
0)
#1110000
b10100100 4
b111010 A
1)
#1112000
0)
#1114000
b10100101 4
b111011 A
1)
#1116000
0)
#1118000
b10100110 4
b111100 A
1)
#1120000
0)
#1122000
b10100111 4
b111101 A
1)
#1124000
0)
#1126000
b10101000 4
b111110 A
1)
#1128000
0)
#1130000
b10101001 4
b111111 A
1)
#1132000
0)
#1134000
b10101010 4
b1000000 A
1)
#1136000
0)
#1138000
b10101011 4
b1000001 A
1)
#1140000
0)
#1142000
b10101100 4
b1000010 A
1)
#1144000
0)
#1146000
b10101101 4
b1000011 A
1)
#1148000
0)
#1150000
b10101110 4
b1000100 A
1)
#1152000
0)
#1154000
b10101111 4
b1000101 A
1)
#1156000
0)
#1158000
b10110000 4
b1000110 A
1)
#1160000
0)
#1162000
b10110001 4
b1000111 A
1)
#1164000
0)
#1166000
b10110010 4
b1001000 A
1)
#1168000
0)
#1170000
b10110011 4
b1001001 A
1)
#1172000
0)
#1174000
b10110100 4
b1001010 A
1)
#1176000
0)
#1178000
b10110101 4
b1001011 A
1)
#1180000
0)
#1182000
b10110110 4
b1001100 A
1)
#1184000
0)
#1186000
b10110111 4
b1001101 A
1)
#1188000
0)
#1190000
b10111000 4
b1001110 A
1)
#1192000
0)
#1194000
b10111001 4
b1001111 A
1)
#1196000
0)
#1198000
b10111010 4
b1010000 A
1)
#1200000
0)
#1202000
b10111011 4
b1010001 A
1)
#1204000
0)
#1206000
b10111100 4
b1010010 A
1)
#1208000
0)
#1210000
b10111101 4
b1010011 A
1)
#1212000
0)
#1214000
b10111110 4
b1010100 A
1)
#1216000
0)
#1218000
b10111111 4
b1010101 A
1)
#1220000
0)
#1222000
b11000000 4
b1010110 A
1)
#1224000
0)
#1226000
b11000001 4
b1010111 A
1)
#1228000
0)
#1230000
b11000010 4
b1011000 A
1)
#1232000
0)
#1234000
b11000011 4
b1011001 A
1)
#1236000
0)
#1238000
b11000100 4
b1011010 A
1)
#1240000
0)
#1242000
b11000101 4
b1011011 A
1)
#1244000
0)
#1246000
b11000110 4
b1011100 A
1)
#1248000
0)
#1250000
b11000111 4
b1011101 A
1)
#1252000
0)
#1254000
b11001000 4
b1011110 A
1)
#1256000
0)
#1258000
b11001001 4
b1011111 A
1)
#1260000
0)
#1262000
b11001010 4
b1100000 A
1)
#1264000
0)
#1266000
b11001011 4
b1100001 A
1)
#1268000
0)
#1270000
b11001100 4
b1100010 A
1)
#1272000
0)
#1274000
b11001101 4
b1100011 A
1)
#1276000
0)
#1278000
b11001110 4
b1100100 A
1)
#1280000
0)
#1282000
b11001111 4
b1100101 A
1)
#1284000
0)
#1286000
b11010000 4
b1100110 A
1)
#1288000
0)
#1290000
b11010001 4
b1100111 A
1)
#1292000
0)
#1294000
b11010010 4
b1101000 A
1)
#1296000
0)
#1298000
b11010011 4
b1101001 A
1)
#1300000
0)
#1302000
b11010100 4
b1101010 A
1)
#1304000
0)
#1306000
b11010101 4
b1101011 A
1)
#1308000
0)
#1310000
b11010110 4
b1101100 A
1)
#1312000
0)
#1314000
b11010111 4
b1101101 A
1)
#1316000
0)
#1318000
b11011000 4
b1101110 A
1)
#1320000
0)
#1322000
b1 3
b1 %
b1 ,
b1 5
b0 4
b1101111 A
1)
#1324000
0)
#1326000
b1 4
b1110000 A
1)
#1328000
0)
#1330000
b10 4
b1110001 A
1)
#1332000
0)
#1334000
b11 4
b1110010 A
1)
#1336000
0)
#1338000
b100 4
b1110011 A
1)
#1340000
0)
#1342000
b101 4
b1110100 A
1)
#1344000
0)
#1346000
b110 4
b1110101 A
1)
#1348000
0)
#1350000
b111 4
b1110110 A
1)
#1352000
0)
#1354000
b1000 4
b1110111 A
1)
#1356000
0)
#1358000
b1001 4
b1111000 A
1)
#1360000
0)
#1362000
b1010 4
b1111001 A
1)
#1364000
0)
#1366000
b1011 4
b1111010 A
1)
#1368000
0)
