ALU/ALU.v
module ALU (
           input [31:0] A,B,    // ALU 32-bit Inputs                 
           input [3:0] select,  // ALU 4-bit Selection
           output [31:0] out,   // ALU 32-bit Output
           output carry         // Carry Flag
           );
           
        reg [31:0] ALU_Result;
        wire [32:0] tmp;
        assign out = ALU_Result;  // ALU output
        assign tmp = {1'b0,A} + {1'b0,B};
        assign carry = tmp[32];   // carry flag
        always @(*)
            begin
            case(select)

                  4'b0000: // Addition
                  ALU_Result = A + B ; 
                  4'b0001: // Subtraction
                  ALU_Result = A - B ;
                  4'b0010: // Multiplication
                  ALU_Result = A * B;
                  4'b0011: // Division
                  ALU_Result = A/B;
                  4'b0100: // Logical shift left
                  ALU_Result = A<<1;
                  4'b0101: // Logical shift right
                  ALU_Result = A>>1;
                  4'b0110: // Rotate left
                  ALU_Result = {A[30:0],A[31]};
                  4'b0111: // Rotate right
                  ALU_Result = {A[0],A[31:1]};
                  4'b1000: //  Logical and 
                  ALU_Result = A & B;
                  4'b1001: //  Logical or
                  ALU_Result = A | B;
                  4'b1010: //  Logical xor 
                  ALU_Result = A ^ B;
                  4'b1011: //  Logical nor
                  ALU_Result = ~(A | B);
                  4'b1100: // Logical nand 
                  ALU_Result = ~(A & B);
                  4'b1101: // Logical xnor
                  ALU_Result = ~(A ^ B);
                  4'b1110: // Greater comparison
                  ALU_Result = (A>B)?32'd1:32'd0 ;
                  4'b1111: // Equal comparison   
                  ALU_Result = (A==B)?32'd1:32'd0 ;
          default: ALU_Result = A + B ; 

        endcase
    end
endmodule

ALU/ALU_tb.v
`include "ALU.v"
`timescale 1ns / 1ps  

module ALU_tb;

 reg[31:0] A,B;
 reg[3:0] select;
 wire[31:0] out;
 wire carry;
 integer i;

 ALU test_unit(
               A,B,     // ALU 32-bit Inputs                 
               select,  // ALU Selection
               out,     // ALU 32-bit Output
               carry    // Carry Out Flag
              );

    initial begin

      $dumpfile("ALU.vcd");
      $dumpvars(0,ALU_tb);
      
      A = 32'h001A;
      B = 32'h00B2;
      select = 4'h0;

      for (i=0 ; i<=15 ; i = i+1)
      begin
       #10;
       select = select + 8'h01;
       #10;
      end;

      A = 32'h00F6;
      B = 32'h000A;  
    end
endmodule

ALU/ALU.vcd
$date
	Wed Mar 15 10:36:09 2023
$end
$version
	Icarus Verilog
$end
$timescale
	1ps
$end
$scope module ALU_tb $end
$var wire 32 ! out [31:0] $end
$var wire 1 " carry $end
$var reg 32 # A [31:0] $end
$var reg 32 $ B [31:0] $end
$var reg 4 % select [3:0] $end
$var integer 32 & i [31:0] $end
$scope module test_unit $end
$var wire 32 ' A [31:0] $end
$var wire 32 ( B [31:0] $end
$var wire 32 ) out [31:0] $end
$var wire 4 * select [3:0] $end
$var wire 33 + tmp [32:0] $end
$var wire 1 " carry $end
$var reg 32 , ALU_Result [31:0] $end
$upscope $end
$upscope $end
$enddefinitions $end
$comment Show the parameter values. $end
$dumpall
$end
#0
$dumpvars
b11001100 ,
b11001100 +
b0 *
b11001100 )
b10110010 (
b11010 '
b0 &
b0 %
b10110010 $
b11010 #
0"
b11001100 !
$end
#10000
b11111111111111111111111101101000 !
b11111111111111111111111101101000 )
b11111111111111111111111101101000 ,
b1 %
b1 *
#20000
b1 &
#30000
b1001000010100 !
b1001000010100 )
b1001000010100 ,
b10 %
b10 *
#40000
b10 &
#50000
b0 !
b0 )
b0 ,
b11 %
b11 *
#60000
b11 &
#70000
b110100 !
b110100 )
b110100 ,
b100 %
b100 *
#80000
b100 &
#90000
b1101 !
b1101 )
b1101 ,
b101 %
b101 *
#100000
b101 &
#110000
b110100 !
b110100 )
b110100 ,
b110 %
b110 *
#120000
b110 &
#130000
b1101 !
b1101 )
b1101 ,
b111 %
b111 *
#140000
b111 &
#150000
b10010 !
b10010 )
b10010 ,
b1000 %
b1000 *
#160000
b1000 &
#170000
b10111010 !
b10111010 )
b10111010 ,
b1001 %
b1001 *
#180000
b1001 &
#190000
b10101000 !
b10101000 )
b10101000 ,
b1010 %
b1010 *
#200000
b1010 &
#210000
b11111111111111111111111101000101 !
b11111111111111111111111101000101 )
b11111111111111111111111101000101 ,
b1011 %
b1011 *
#220000
b1011 &
#230000
b11111111111111111111111111101101 !
b11111111111111111111111111101101 )
b11111111111111111111111111101101 ,
b1100 %
b1100 *
#240000
b1100 &
#250000
b11111111111111111111111101010111 !
b11111111111111111111111101010111 )
b11111111111111111111111101010111 ,
b1101 %
b1101 *
#260000
b1101 &
#270000
b0 !
b0 )
b0 ,
b1110 %
b1110 *
#280000
b1110 &
#290000
b1111 %
b1111 *
#300000
b1111 &
#310000
b11001100 !
b11001100 )
b11001100 ,
b0 %
b0 *
#320000
b100000000 !
b100000000 )
b100000000 ,
b1010 $
b1010 (
b100000000 +
b11110110 #
b11110110 '
b10000 &
